{"total": {"value": 10, "relation": "eq"}, "query": {"from": 0, "size": 200}, "filings": [{"ticker": "CAT", "formType": "10-K", "accessionNo": "0000018230-10-000092", "cik": "18230", "companyNameLong": "CATERPILLAR INC (Filer)", "companyName": "CATERPILLAR INC", "linkToFilingDetails": "https://www.sec.gov/Archives/edgar/data/18230/000001823010000092/form10k_2009.htm", "description": "Form 10-K - Annual report [Section 13 and 15(d), not S-K Item 405]", "linkToTxt": "https://www.sec.gov/Archives/edgar/data/18230/000001823010000092/0000018230-10-000092.txt", "filedAt": "2010-02-19T12:42:45-05:00", "documentFormatFiles": [{"sequence": "1", "size": "589020", "documentUrl": "https://www.sec.gov/Archives/edgar/data/18230/000001823010000092/form10k_2009.htm", "description": "2009 FORM 10-K", "type": "10-K"}, {"sequence": "2", "size": "170948", "documentUrl": "https://www.sec.gov/Archives/edgar/data/18230/000001823010000092/ex_10-4.htm", "description": "SUPPLEMENTAL EMPLOYEES' INVESTMENT PLAN", "type": "EX-10.4"}, {"sequence": "3", "size": "37601", "documentUrl": "https://www.sec.gov/Archives/edgar/data/18230/000001823010000092/ex_10-5.htm", "description": "EXECUTIVE SHORT-TERM INCENTIVE PLAN", "type": "EX-10.5"}, {"sequence": "4", "size": "164631", "documentUrl": "https://www.sec.gov/Archives/edgar/data/18230/000001823010000092/ex_10-8.htm", "description": "DEFERRED EMPLOYEES' INVESTMENT PLAN", "type": "EX-10.8"}, {"sequence": "5", "size": "139480", "documentUrl": "https://www.sec.gov/Archives/edgar/data/18230/000001823010000092/ex_10-9.htm", "description": "SOLAR MANAGERIAL RETIREMENT OBJECTIVE PLAN", "type": "EX-10.9"}, {"sequence": "6", "size": "144248", "documentUrl": "https://www.sec.gov/Archives/edgar/data/18230/000001823010000092/ex_10-10.htm", "description": "SOLAR PENSION PLAN FOR EUROPEAN FOREIGN SERVICE", "type": "EX-10.10"}, {"sequence": "7", "size": "22060", "documentUrl": "https://www.sec.gov/Archives/edgar/data/18230/000001823010000092/ex_11.htm", "description": "COMPUTATIONS OF EARNINGS PER SHARE", "type": "EX-11"}, {"sequence": "8", "size": "46953", "documentUrl": "https://www.sec.gov/Archives/edgar/data/18230/000001823010000092/ex_12.htm", "description": "COMPUTATIONS OF RATIOS OF EARNINGS TO FIXED CHARGES", "type": "EX-12"}, {"sequence": "9", "size": "17210165", "documentUrl": "https://www.sec.gov/Archives/edgar/data/18230/000001823010000092/ex_13.htm", "description": "GENERAL AND FINANCIAL INFORMATION FOR 2009", "type": "EX-13"}, {"sequence": "10", "size": "346432", "documentUrl": "https://www.sec.gov/Archives/edgar/data/18230/000001823010000092/ex_21.htm", "description": "SUBSIDIARIES AND AFFILIATES OF THE REGISTRANT", "type": "EX-21"}, {"sequence": "11", "size": "3777", "documentUrl": "https://www.sec.gov/Archives/edgar/data/18230/000001823010000092/ex_23.htm", "description": "CONSENT OF INDEPENDENT REGISTERED PUBLIC ACCOUNTING FIRM", "type": "EX-23"}, {"sequence": "12", "size": "19467", "documentUrl": "https://www.sec.gov/Archives/edgar/data/18230/000001823010000092/ex_31-1.htm", "description": "CERTIFICATION OF CEO", "type": "EX-31.1"}, {"sequence": "13", "size": "19496", "documentUrl": "https://www.sec.gov/Archives/edgar/data/18230/000001823010000092/ex_31-2.htm", "description": "CERTIFICATION OF CFO", "type": "EX-31.2"}, {"sequence": "14", "size": "11577", "documentUrl": "https://www.sec.gov/Archives/edgar/data/18230/000001823010000092/ex_32.htm", "description": "SECTION 906 CERTIFICATION", "type": "EX-32"}, {"sequence": "21", "size": "51592", "documentUrl": "https://www.sec.gov/Archives/edgar/data/18230/000001823010000092/image_1.jpg", "type": "GRAPHIC"}, {"sequence": "22", "size": "74824", "documentUrl": "https://www.sec.gov/Archives/edgar/data/18230/000001823010000092/image_2.jpg", "type": "GRAPHIC"}, {"sequence": "23", "size": "57041", "documentUrl": "https://www.sec.gov/Archives/edgar/data/18230/000001823010000092/image_3.jpg", "type": "GRAPHIC"}, {"sequence": "24", "size": "80178", "documentUrl": "https://www.sec.gov/Archives/edgar/data/18230/000001823010000092/image_4.jpg", "type": "GRAPHIC"}, {"sequence": "25", "size": "52432", "documentUrl": "https://www.sec.gov/Archives/edgar/data/18230/000001823010000092/image_5.jpg", "type": "GRAPHIC"}, {"sequence": "26", "size": "61466", "documentUrl": "https://www.sec.gov/Archives/edgar/data/18230/000001823010000092/image_6.jpg", "type": "GRAPHIC"}, {"sequence": "27", "size": "56656", "documentUrl": "https://www.sec.gov/Archives/edgar/data/18230/000001823010000092/image_7.jpg", "type": "GRAPHIC"}, {"sequence": "28", "size": "6757", "documentUrl": "https://www.sec.gov/Archives/edgar/data/18230/000001823010000092/cat_logo.jpg", "type": "GRAPHIC"}, {"sequence": "29", "size": "9372", "documentUrl": "https://www.sec.gov/Archives/edgar/data/18230/000001823010000092/pwc_logo.jpg", "type": "GRAPHIC"}, {"sequence": "30", "size": "1401030", "documentUrl": "https://www.sec.gov/Archives/edgar/data/18230/000001823010000092/form10k_2009.pdf", "type": "10-K"}, {"sequence": "\u00a0", "size": "32681880", "documentUrl": "https://www.sec.gov/Archives/edgar/data/18230/000001823010000092/0000018230-10-000092.txt", "description": "Complete submission text file", "type": "\u00a0"}], "periodOfReport": "2009-12-31", "entities": [{"fiscalYearEnd": "1231", "stateOfIncorporation": "DE", "act": "34", "cik": "18230", "fileNo": "001-00768", "irsNo": "370602744", "companyName": "CATERPILLAR INC (Filer)", "type": "10-K", "sic": "3531 Construction Machinery &amp; Equip", "filmNo": "10618847"}], "id": "3fabd2d1cfbe734f5a7b9b36d6f9bd6e", "seriesAndClassesContractsInformation": [], "linkToHtml": "https://www.sec.gov/Archives/edgar/data/18230/0000018230-10-000092-index.htm", "linkToXbrl": "", "dataFiles": [{"sequence": "15", "size": "55525", "documentUrl": "https://www.sec.gov/Archives/edgar/data/18230/000001823010000092/cat-20091231_cal.xml", "type": "EX-101.CAL"}, {"sequence": "16", "size": "31622", "documentUrl": "https://www.sec.gov/Archives/edgar/data/18230/000001823010000092/cat-20091231_def.xml", "type": "EX-101.DEF"}, {"sequence": "17", "size": "304770", "documentUrl": "https://www.sec.gov/Archives/edgar/data/18230/000001823010000092/cat-20091231_lab.xml", "type": "EX-101.LAB"}, {"sequence": "18", "size": "153873", "documentUrl": "https://www.sec.gov/Archives/edgar/data/18230/000001823010000092/cat-20091231_pre.xml", "type": "EX-101.PRE"}, {"sequence": "19", "size": "4800731", "documentUrl": "https://www.sec.gov/Archives/edgar/data/18230/000001823010000092/cat-20091231.xml", "type": "EX-101.INS"}, {"sequence": "20", "size": "27296", "documentUrl": "https://www.sec.gov/Archives/edgar/data/18230/000001823010000092/cat-20091231.xsd", "type": "EX-101.SCH"}]}, {"ticker": "CAT", "formType": "10-K", "accessionNo": "0001104659-11-008938", "cik": "18230", "companyNameLong": "CATERPILLAR INC (Filer)", "companyName": "CATERPILLAR INC", "linkToFilingDetails": "https://www.sec.gov/Archives/edgar/data/18230/000110465911008938/a10-18643_110k.htm", "description": "Form 10-K - Annual report [Section 13 and 15(d), not S-K Item 405]", "linkToTxt": "https://www.sec.gov/Archives/edgar/data/18230/000110465911008938/0001104659-11-008938.txt", "filedAt": "2011-02-22T17:15:14-05:00", "documentFormatFiles": [{"sequence": "1", "size": "597765", "documentUrl": "https://www.sec.gov/Archives/edgar/data/18230/000110465911008938/a10-18643_110k.htm", "description": "10-K", "type": "10-K"}, {"sequence": "2", "size": "58467", "documentUrl": "https://www.sec.gov/Archives/edgar/data/18230/000110465911008938/a10-18643_1ex3d2.htm", "description": "EX-3.2", "type": "EX-3.2"}, {"sequence": "3", "size": "199849", "documentUrl": "https://www.sec.gov/Archives/edgar/data/18230/000110465911008938/a10-18643_1ex10d2.htm", "description": "EX-10.2", "type": "EX-10.2"}, {"sequence": "4", "size": "223597", "documentUrl": "https://www.sec.gov/Archives/edgar/data/18230/000110465911008938/a10-18643_1ex10d5.htm", "description": "EX-10.5", "type": "EX-10.5"}, {"sequence": "5", "size": "291722", "documentUrl": "https://www.sec.gov/Archives/edgar/data/18230/000110465911008938/a10-18643_1ex10d11.htm", "description": "EX-10.11", "type": "EX-10.11"}, {"sequence": "6", "size": "31575", "documentUrl": "https://www.sec.gov/Archives/edgar/data/18230/000110465911008938/a10-18643_1ex11.htm", "description": "EX-11", "type": "EX-11"}, {"sequence": "7", "size": "48474", "documentUrl": "https://www.sec.gov/Archives/edgar/data/18230/000110465911008938/a10-18643_1ex12.htm", "description": "EX-12", "type": "EX-12"}, {"sequence": "8", "size": "6969142", "documentUrl": "https://www.sec.gov/Archives/edgar/data/18230/000110465911008938/a10-18643_1ex13.htm", "description": "EX-13", "type": "EX-13"}, {"sequence": "9", "size": "325136", "documentUrl": "https://www.sec.gov/Archives/edgar/data/18230/000110465911008938/a10-18643_1ex21.htm", "description": "EX-21", "type": "EX-21"}, {"sequence": "10", "size": "2882", "documentUrl": "https://www.sec.gov/Archives/edgar/data/18230/000110465911008938/a10-18643_1ex23.htm", "description": "EX-23", "type": "EX-23"}, {"sequence": "11", "size": "19470", "documentUrl": "https://www.sec.gov/Archives/edgar/data/18230/000110465911008938/a10-18643_1ex31d1.htm", "description": "EX-31.1", "type": "EX-31.1"}, {"sequence": "12", "size": "19464", "documentUrl": "https://www.sec.gov/Archives/edgar/data/18230/000110465911008938/a10-18643_1ex31d2.htm", "description": "EX-31.2", "type": "EX-31.2"}, {"sequence": "13", "size": "12699", "documentUrl": "https://www.sec.gov/Archives/edgar/data/18230/000110465911008938/a10-18643_1ex32.htm", "description": "EX-32", "type": "EX-32"}, {"sequence": "20", "size": "5374", "documentUrl": "https://www.sec.gov/Archives/edgar/data/18230/000110465911008938/g186431ke27i001.gif", "description": "GRAPHIC", "type": "GRAPHIC"}, {"sequence": "21", "size": "3304", "documentUrl": "https://www.sec.gov/Archives/edgar/data/18230/000110465911008938/g186431ba01i001.jpg", "description": "GRAPHIC", "type": "GRAPHIC"}, {"sequence": "22", "size": "4708", "documentUrl": "https://www.sec.gov/Archives/edgar/data/18230/000110465911008938/g186431ke19i001.gif", "description": "GRAPHIC", "type": "GRAPHIC"}, {"sequence": "23", "size": "5616", "documentUrl": "https://www.sec.gov/Archives/edgar/data/18230/000110465911008938/g186431ke19i002.gif", "description": "GRAPHIC", "type": "GRAPHIC"}, {"sequence": "24", "size": "5717", "documentUrl": "https://www.sec.gov/Archives/edgar/data/18230/000110465911008938/g186431ke19i003.gif", "description": "GRAPHIC", "type": "GRAPHIC"}, {"sequence": "25", "size": "4824", "documentUrl": "https://www.sec.gov/Archives/edgar/data/18230/000110465911008938/g186431ke21i001.gif", "description": "GRAPHIC", "type": "GRAPHIC"}, {"sequence": "26", "size": "3917", "documentUrl": "https://www.sec.gov/Archives/edgar/data/18230/000110465911008938/g186431ke21i002.gif", "description": "GRAPHIC", "type": "GRAPHIC"}, {"sequence": "27", "size": "25611", "documentUrl": "https://www.sec.gov/Archives/edgar/data/18230/000110465911008938/g186431ke23i001.jpg", "description": "GRAPHIC", "type": "GRAPHIC"}, {"sequence": "28", "size": "3851158", "documentUrl": "https://www.sec.gov/Archives/edgar/data/18230/000110465911008938/a18643-1_form10k2010.pdf", "description": "10-K PDF WITH EXHIBITS", "type": "10-K"}, {"sequence": "\u00a0", "size": "73688324", "documentUrl": "https://www.sec.gov/Archives/edgar/data/18230/000110465911008938/0001104659-11-008938.txt", "description": "Complete submission text file", "type": "\u00a0"}], "entities": [{"fiscalYearEnd": "1231", "stateOfIncorporation": "DE", "act": "34", "cik": "0000018230", "fileNo": "001-00768", "irsNo": "370602744", "companyName": "CATERPILLAR INC (Filer)", "type": "10-K", "sic": "3531 Construction Machinery &amp; Equip", "filmNo": "11629423"}], "id": "fb5146a2d3460569fced1e41ae12cfcd", "seriesAndClassesContractsInformation": [], "linkToHtml": "https://www.sec.gov/Archives/edgar/data/18230/0001104659-11-008938-index.htm", "linkToXbrl": "", "dataFiles": [{"sequence": "14", "size": "11890245", "documentUrl": "https://www.sec.gov/Archives/edgar/data/18230/000110465911008938/cat-20101231.xml", "description": "EX-101.INS", "type": "EX-101.INS"}, {"sequence": "15", "size": "266750", "documentUrl": "https://www.sec.gov/Archives/edgar/data/18230/000110465911008938/cat-20101231.xsd", "description": "EX-101.SCH", "type": "EX-101.SCH"}, {"sequence": "16", "size": "242703", "documentUrl": "https://www.sec.gov/Archives/edgar/data/18230/000110465911008938/cat-20101231_cal.xml", "description": "EX-101.CAL", "type": "EX-101.CAL"}, {"sequence": "17", "size": "3359093", "documentUrl": "https://www.sec.gov/Archives/edgar/data/18230/000110465911008938/cat-20101231_lab.xml", "description": "EX-101.LAB", "type": "EX-101.LAB"}, {"sequence": "18", "size": "1419608", "documentUrl": "https://www.sec.gov/Archives/edgar/data/18230/000110465911008938/cat-20101231_pre.xml", "description": "EX-101.PRE", "type": "EX-101.PRE"}, {"sequence": "19", "size": "1004734", "documentUrl": "https://www.sec.gov/Archives/edgar/data/18230/000110465911008938/cat-20101231_def.xml", "description": "EX-101.DEF", "type": "EX-101.DEF"}]}, {"ticker": "CAT", "formType": "10-K", "accessionNo": "0001104659-12-011331", "cik": "18230", "companyNameLong": "CATERPILLAR INC (Filer)", "companyName": "CATERPILLAR INC", "linkToFilingDetails": "https://www.sec.gov/Archives/edgar/data/18230/000110465912011331/a12-2184_110k.htm", "description": "Form 10-K - Annual report [Section 13 and 15(d), not S-K Item 405]", "linkToTxt": "https://www.sec.gov/Archives/edgar/data/18230/000110465912011331/0001104659-12-011331.txt", "filedAt": "2012-02-21T15:49:01-05:00", "documentFormatFiles": [{"sequence": "1", "size": "597517", "documentUrl": "https://www.sec.gov/Archives/edgar/data/18230/000110465912011331/a12-2184_110k.htm", "description": "10-K", "type": "10-K"}, {"sequence": "2", "size": "1598324", "documentUrl": "https://www.sec.gov/Archives/edgar/data/18230/000110465912011331/a12-2184_110k.pdf", "description": "10-K PDF WITH EXHIBITS", "type": "10-K"}, {"sequence": "3", "size": "19337", "documentUrl": "https://www.sec.gov/Archives/edgar/data/18230/000110465912011331/a12-2184_1ex10d3.htm", "description": "EX-10.3", "type": "EX-10.3"}, {"sequence": "4", "size": "112675", "documentUrl": "https://www.sec.gov/Archives/edgar/data/18230/000110465912011331/a12-2184_1ex10d12.htm", "description": "EX-10.12", "type": "EX-10.12"}, {"sequence": "5", "size": "123660", "documentUrl": "https://www.sec.gov/Archives/edgar/data/18230/000110465912011331/a12-2184_1ex10d13.htm", "description": "EX-10.13", "type": "EX-10.13"}, {"sequence": "6", "size": "31625", "documentUrl": "https://www.sec.gov/Archives/edgar/data/18230/000110465912011331/a12-2184_1ex11.htm", "description": "EX-11", "type": "EX-11"}, {"sequence": "7", "size": "49543", "documentUrl": "https://www.sec.gov/Archives/edgar/data/18230/000110465912011331/a12-2184_1ex12.htm", "description": "EX-12", "type": "EX-12"}, {"sequence": "8", "size": "7605442", "documentUrl": "https://www.sec.gov/Archives/edgar/data/18230/000110465912011331/a12-2184_1ex13.htm", "description": "EX-13", "type": "EX-13"}, {"sequence": "9", "size": "400960", "documentUrl": "https://www.sec.gov/Archives/edgar/data/18230/000110465912011331/a12-2184_1ex21.htm", "description": "EX-21", "type": "EX-21"}, {"sequence": "10", "size": "2898", "documentUrl": "https://www.sec.gov/Archives/edgar/data/18230/000110465912011331/a12-2184_1ex23.htm", "description": "EX-23", "type": "EX-23"}, {"sequence": "11", "size": "14099", "documentUrl": "https://www.sec.gov/Archives/edgar/data/18230/000110465912011331/a12-2184_1ex31d1.htm", "description": "EX-31.1", "type": "EX-31.1"}, {"sequence": "12", "size": "14028", "documentUrl": "https://www.sec.gov/Archives/edgar/data/18230/000110465912011331/a12-2184_1ex31d2.htm", "description": "EX-31.2", "type": "EX-31.2"}, {"sequence": "13", "size": "11795", "documentUrl": "https://www.sec.gov/Archives/edgar/data/18230/000110465912011331/a12-2184_1ex32.htm", "description": "EX-32", "type": "EX-32"}, {"sequence": "14", "size": "291335", "documentUrl": "https://www.sec.gov/Archives/edgar/data/18230/000110465912011331/a12-2184_1ex95.htm", "description": "EX-95", "type": "EX-95"}, {"sequence": "21", "size": "20644", "documentUrl": "https://www.sec.gov/Archives/edgar/data/18230/000110465912011331/g21841ke31i001.jpg", "description": "GRAPHIC", "type": "GRAPHIC"}, {"sequence": "22", "size": "21846", "documentUrl": "https://www.sec.gov/Archives/edgar/data/18230/000110465912011331/g21841ke31i002.jpg", "description": "GRAPHIC", "type": "GRAPHIC"}, {"sequence": "23", "size": "22617", "documentUrl": "https://www.sec.gov/Archives/edgar/data/18230/000110465912011331/g21841ke33i001.jpg", "description": "GRAPHIC", "type": "GRAPHIC"}, {"sequence": "24", "size": "24903", "documentUrl": "https://www.sec.gov/Archives/edgar/data/18230/000110465912011331/g21841ke33i002.jpg", "description": "GRAPHIC", "type": "GRAPHIC"}, {"sequence": "25", "size": "21231", "documentUrl": "https://www.sec.gov/Archives/edgar/data/18230/000110465912011331/g21841ke29i001.jpg", "description": "GRAPHIC", "type": "GRAPHIC"}, {"sequence": "26", "size": "23016", "documentUrl": "https://www.sec.gov/Archives/edgar/data/18230/000110465912011331/g21841ke29i002.jpg", "description": "GRAPHIC", "type": "GRAPHIC"}, {"sequence": "27", "size": "38530", "documentUrl": "https://www.sec.gov/Archives/edgar/data/18230/000110465912011331/g21841ke39i001.gif", "description": "GRAPHIC", "type": "GRAPHIC"}, {"sequence": "28", "size": "3334", "documentUrl": "https://www.sec.gov/Archives/edgar/data/18230/000110465912011331/g21841ba01i001.jpg", "description": "GRAPHIC", "type": "GRAPHIC"}, {"sequence": "\u00a0", "size": "63153386", "documentUrl": "https://www.sec.gov/Archives/edgar/data/18230/000110465912011331/0001104659-12-011331.txt", "description": "Complete submission text file", "type": "\u00a0"}], "entities": [{"fiscalYearEnd": "1231", "stateOfIncorporation": "DE", "act": "34", "cik": "0000018230", "fileNo": "001-00768", "irsNo": "370602744", "companyName": "CATERPILLAR INC (Filer)", "type": "10-K", "sic": "3531 Construction Machinery &amp; Equip", "filmNo": "12626789"}], "id": "5d3e4ee3d53058aec61320d59dc2516c", "seriesAndClassesContractsInformation": [], "linkToHtml": "https://www.sec.gov/Archives/edgar/data/18230/0001104659-12-011331-index.htm", "linkToXbrl": "", "dataFiles": [{"sequence": "15", "size": "12710865", "documentUrl": "https://www.sec.gov/Archives/edgar/data/18230/000110465912011331/cat-20111231.xml", "description": "XBRL INSTANCE DOCUMENT", "type": "EX-101.INS"}, {"sequence": "16", "size": "267379", "documentUrl": "https://www.sec.gov/Archives/edgar/data/18230/000110465912011331/cat-20111231.xsd", "description": "XBRL TAXONOMY EXTENSION SCHEMA DOCUMENT", "type": "EX-101.SCH"}, {"sequence": "17", "size": "263798", "documentUrl": "https://www.sec.gov/Archives/edgar/data/18230/000110465912011331/cat-20111231_cal.xml", "description": "XBRL TAXONOMY EXTENSION CALCULATION LINKBASE DOCUMENT", "type": "EX-101.CAL"}, {"sequence": "18", "size": "1117154", "documentUrl": "https://www.sec.gov/Archives/edgar/data/18230/000110465912011331/cat-20111231_def.xml", "description": "XBRL TAXONOMY EXTENSION DEFINITION LINKBASE DOCUMENT", "type": "EX-101.DEF"}, {"sequence": "19", "size": "3823916", "documentUrl": "https://www.sec.gov/Archives/edgar/data/18230/000110465912011331/cat-20111231_lab.xml", "description": "XBRL TAXONOMY EXTENSION LABELS LINKBASE DOCUMENT", "type": "EX-101.LAB"}, {"sequence": "20", "size": "1658125", "documentUrl": "https://www.sec.gov/Archives/edgar/data/18230/000110465912011331/cat-20111231_pre.xml", "description": "XBRL TAXONOMY EXTENSION PRESENTATION LINKBASE DOCUMENT", "type": "EX-101.PRE"}]}, {"ticker": "CAT", "formType": "10-K", "accessionNo": "0000018230-13-000075", "cik": "18230", "companyNameLong": "CATERPILLAR INC (Filer)", "companyName": "CATERPILLAR INC", "linkToFilingDetails": "https://www.sec.gov/Archives/edgar/data/18230/000001823013000075/cat_10-kx12312012.htm", "description": "Form 10-K - Annual report [Section 13 and 15(d), not S-K Item 405]", "linkToTxt": "https://www.sec.gov/Archives/edgar/data/18230/000001823013000075/0000018230-13-000075.txt", "filedAt": "2013-02-19T12:26:30-05:00", "documentFormatFiles": [{"sequence": "1", "size": "582326", "documentUrl": "https://www.sec.gov/Archives/edgar/data/18230/000001823013000075/cat_10-kx12312012.htm", "description": "10-K", "type": "10-K"}, {"sequence": "2", "size": "2643515", "documentUrl": "https://www.sec.gov/Archives/edgar/data/18230/000001823013000075/a10kpdfwithexhibits.pdf", "description": "10-K PDF WITH EXHIBITS", "type": "10-K"}, {"sequence": "3", "size": "25971", "documentUrl": "https://www.sec.gov/Archives/edgar/data/18230/000001823013000075/ex103.htm", "description": "EXHIBIT", "type": "EX-10.3"}, {"sequence": "4", "size": "22467", "documentUrl": "https://www.sec.gov/Archives/edgar/data/18230/000001823013000075/ex104.htm", "description": "EXHIBIT", "type": "EX-10.4"}, {"sequence": "5", "size": "23031", "documentUrl": "https://www.sec.gov/Archives/edgar/data/18230/000001823013000075/ex105.htm", "description": "EXHIBIT", "type": "EX-10.5"}, {"sequence": "6", "size": "157809", "documentUrl": "https://www.sec.gov/Archives/edgar/data/18230/000001823013000075/ex106.htm", "description": "EXHIBIT", "type": "EX-10.6"}, {"sequence": "7", "size": "141175", "documentUrl": "https://www.sec.gov/Archives/edgar/data/18230/000001823013000075/ex107.htm", "description": "EXHIBIT", "type": "EX-10.7"}, {"sequence": "8", "size": "142757", "documentUrl": "https://www.sec.gov/Archives/edgar/data/18230/000001823013000075/ex1011.htm", "description": "EXHIBIT", "type": "EX-10.11"}, {"sequence": "9", "size": "222777", "documentUrl": "https://www.sec.gov/Archives/edgar/data/18230/000001823013000075/ex1012.htm", "description": "EXHIBIT", "type": "EX-10.12"}, {"sequence": "10", "size": "117447", "documentUrl": "https://www.sec.gov/Archives/edgar/data/18230/000001823013000075/ex1013.htm", "description": "EXHIBIT", "type": "EX-10.13"}, {"sequence": "11", "size": "117087", "documentUrl": "https://www.sec.gov/Archives/edgar/data/18230/000001823013000075/ex1014.htm", "description": "EXHIBIT", "type": "EX-10.14"}, {"sequence": "12", "size": "29968", "documentUrl": "https://www.sec.gov/Archives/edgar/data/18230/000001823013000075/cat_exhibit11x12312012.htm", "description": "EXHIBIT", "type": "EX-11"}, {"sequence": "13", "size": "48461", "documentUrl": "https://www.sec.gov/Archives/edgar/data/18230/000001823013000075/cat_exhibit12x12312012.htm", "description": "EXHIBIT", "type": "EX-12"}, {"sequence": "14", "size": "8806571", "documentUrl": "https://www.sec.gov/Archives/edgar/data/18230/000001823013000075/cat_exhibit13x12312012.htm", "description": "EXHIBIT", "type": "EX-13"}, {"sequence": "15", "size": "434824", "documentUrl": "https://www.sec.gov/Archives/edgar/data/18230/000001823013000075/ex_21.htm", "description": "EXHIBIT", "type": "EX-21"}, {"sequence": "16", "size": "3883", "documentUrl": "https://www.sec.gov/Archives/edgar/data/18230/000001823013000075/cat_exhibit23x12312012.htm", "description": "EXHIBIT", "type": "EX-23"}, {"sequence": "17", "size": "15658", "documentUrl": "https://www.sec.gov/Archives/edgar/data/18230/000001823013000075/ex_311.htm", "description": "EXHIBIT", "type": "EX-31.1"}, {"sequence": "18", "size": "15607", "documentUrl": "https://www.sec.gov/Archives/edgar/data/18230/000001823013000075/ex_312.htm", "description": "EXHIBIT", "type": "EX-31.2"}, {"sequence": "19", "size": "12604", "documentUrl": "https://www.sec.gov/Archives/edgar/data/18230/000001823013000075/cat_exhibit32x12312012.htm", "description": "EXHIBIT", "type": "EX-32"}, {"sequence": "20", "size": "168121", "documentUrl": "https://www.sec.gov/Archives/edgar/data/18230/000001823013000075/cat_exhibit95x12312012.htm", "description": "EXHIBIT", "type": "EX-95"}, {"sequence": "27", "size": "96509", "documentUrl": "https://www.sec.gov/Archives/edgar/data/18230/000001823013000075/a4q12operatingprofit.jpg", "type": "GRAPHIC"}, {"sequence": "28", "size": "84075", "documentUrl": "https://www.sec.gov/Archives/edgar/data/18230/000001823013000075/a4q12salesandrevenues.jpg", "type": "GRAPHIC"}, {"sequence": "29", "size": "161389", "documentUrl": "https://www.sec.gov/Archives/edgar/data/18230/000001823013000075/catexhibit1312312012chart.jpg", "type": "GRAPHIC"}, {"sequence": "30", "size": "23016", "documentUrl": "https://www.sec.gov/Archives/edgar/data/18230/000001823013000075/conoperatingprofit.jpg", "type": "GRAPHIC"}, {"sequence": "31", "size": "21231", "documentUrl": "https://www.sec.gov/Archives/edgar/data/18230/000001823013000075/consalesandrevenuescomp.jpg", "type": "GRAPHIC"}, {"sequence": "32", "size": "85739", "documentUrl": "https://www.sec.gov/Archives/edgar/data/18230/000001823013000075/fullyearoperatingprofit.jpg", "type": "GRAPHIC"}, {"sequence": "33", "size": "68758", "documentUrl": "https://www.sec.gov/Archives/edgar/data/18230/000001823013000075/fullyearsalesandrevenues.jpg", "type": "GRAPHIC"}, {"sequence": "34", "size": "3334", "documentUrl": "https://www.sec.gov/Archives/edgar/data/18230/000001823013000075/logoa18.jpg", "type": "GRAPHIC"}, {"sequence": "\u00a0", "size": "74205943", "documentUrl": "https://www.sec.gov/Archives/edgar/data/18230/000001823013000075/0000018230-13-000075.txt", "description": "Complete submission text file", "type": "\u00a0"}], "periodOfReport": "2012-12-31", "entities": [{"fiscalYearEnd": "1231", "stateOfIncorporation": "DE", "act": "34", "cik": "18230", "fileNo": "001-00768", "irsNo": "370602744", "companyName": "CATERPILLAR INC (Filer)", "type": "10-K", "sic": "3531 Construction Machinery &amp; Equip", "filmNo": "13622443"}], "id": "94bb1637d2b8f141d555cd920aba0543", "seriesAndClassesContractsInformation": [], "linkToHtml": "https://www.sec.gov/Archives/edgar/data/18230/0000018230-13-000075-index.htm", "linkToXbrl": "", "dataFiles": [{"sequence": "21", "size": "16928198", "documentUrl": "https://www.sec.gov/Archives/edgar/data/18230/000001823013000075/cat-20121231.xml", "description": "XBRL INSTANCE DOCUMENT", "type": "EX-101.INS"}, {"sequence": "22", "size": "197745", "documentUrl": "https://www.sec.gov/Archives/edgar/data/18230/000001823013000075/cat-20121231.xsd", "description": "XBRL TAXONOMY EXTENSION SCHEMA DOCUMENT", "type": "EX-101.SCH"}, {"sequence": "23", "size": "252181", "documentUrl": "https://www.sec.gov/Archives/edgar/data/18230/000001823013000075/cat-20121231_cal.xml", "description": "XBRL TAXONOMY EXTENSION CALCULATION LINKBASE DOCUMENT", "type": "EX-101.CAL"}, {"sequence": "24", "size": "918510", "documentUrl": "https://www.sec.gov/Archives/edgar/data/18230/000001823013000075/cat-20121231_def.xml", "description": "XBRL TAXONOMY EXTENSION DEFINITION LINKBASE DOCUMENT", "type": "EX-101.DEF"}, {"sequence": "25", "size": "2350893", "documentUrl": "https://www.sec.gov/Archives/edgar/data/18230/000001823013000075/cat-20121231_lab.xml", "description": "XBRL TAXONOMY EXTENSION LABEL LINKBASE DOCUMENT", "type": "EX-101.LAB"}, {"sequence": "26", "size": "1283967", "documentUrl": "https://www.sec.gov/Archives/edgar/data/18230/000001823013000075/cat-20121231_pre.xml", "description": "XBRL TAXONOMY EXTENSION PRESENTATION LINKBASE DOCUMENT", "type": "EX-101.PRE"}]}, {"ticker": "CAT", "formType": "10-K", "accessionNo": "0000018230-14-000058", "cik": "18230", "companyNameLong": "CATERPILLAR INC (Filer)", "companyName": "CATERPILLAR INC", "linkToFilingDetails": "https://www.sec.gov/Archives/edgar/data/18230/000001823014000058/cat_10-kx12312013.htm", "description": "Form 10-K - Annual report [Section 13 and 15(d), not S-K Item 405]", "linkToTxt": "https://www.sec.gov/Archives/edgar/data/18230/000001823014000058/0000018230-14-000058.txt", "filedAt": "2014-02-18T14:25:26-05:00", "documentFormatFiles": [{"sequence": "1", "size": "583428", "documentUrl": "https://www.sec.gov/Archives/edgar/data/18230/000001823014000058/cat_10-kx12312013.htm", "description": "10-K", "type": "10-K"}, {"sequence": "2", "size": "163748", "documentUrl": "https://www.sec.gov/Archives/edgar/data/18230/000001823014000058/ex10-6.htm", "description": "EX-10.6", "type": "EX-10.6"}, {"sequence": "3", "size": "128444", "documentUrl": "https://www.sec.gov/Archives/edgar/data/18230/000001823014000058/ex10-7.htm", "description": "EX-10.7", "type": "EX-10.7"}, {"sequence": "4", "size": "153813", "documentUrl": "https://www.sec.gov/Archives/edgar/data/18230/000001823014000058/ex10-11.htm", "description": "EX-10.11", "type": "EX-10.11"}, {"sequence": "5", "size": "214081", "documentUrl": "https://www.sec.gov/Archives/edgar/data/18230/000001823014000058/ex10-12.htm", "description": "EX-10.12", "type": "EX-10.12"}, {"sequence": "6", "size": "130158", "documentUrl": "https://www.sec.gov/Archives/edgar/data/18230/000001823014000058/ex10-13.htm", "description": "EX-10.13", "type": "EX-10.13"}, {"sequence": "7", "size": "99401", "documentUrl": "https://www.sec.gov/Archives/edgar/data/18230/000001823014000058/ex10-14.htm", "description": "EX-10.14", "type": "EX-10.14"}, {"sequence": "8", "size": "30916", "documentUrl": "https://www.sec.gov/Archives/edgar/data/18230/000001823014000058/cat_exx11x12312013.htm", "description": "EX-11", "type": "EX-11"}, {"sequence": "9", "size": "48977", "documentUrl": "https://www.sec.gov/Archives/edgar/data/18230/000001823014000058/cat_exx12x12312013.htm", "description": "EX-12", "type": "EX-12"}, {"sequence": "10", "size": "8996419", "documentUrl": "https://www.sec.gov/Archives/edgar/data/18230/000001823014000058/cat_exx13x12312013.htm", "description": "EX-13", "type": "EX-13"}, {"sequence": "11", "size": "412961", "documentUrl": "https://www.sec.gov/Archives/edgar/data/18230/000001823014000058/ex21.htm", "description": "EX-21", "type": "EX-21"}, {"sequence": "12", "size": "3888", "documentUrl": "https://www.sec.gov/Archives/edgar/data/18230/000001823014000058/cat_exx23x12312013.htm", "description": "EX-23", "type": "EX-23"}, {"sequence": "13", "size": "15687", "documentUrl": "https://www.sec.gov/Archives/edgar/data/18230/000001823014000058/cat_exx311x12312013.htm", "description": "EX-31.1", "type": "EX-31.1"}, {"sequence": "14", "size": "15560", "documentUrl": "https://www.sec.gov/Archives/edgar/data/18230/000001823014000058/cat_exx312x12312013.htm", "description": "EX-31.2", "type": "EX-31.2"}, {"sequence": "15", "size": "12558", "documentUrl": "https://www.sec.gov/Archives/edgar/data/18230/000001823014000058/cat_exx32x12312013.htm", "description": "EX-32", "type": "EX-32"}, {"sequence": "16", "size": "123403", "documentUrl": "https://www.sec.gov/Archives/edgar/data/18230/000001823014000058/cat_exx95x12312013.htm", "description": "EX-95", "type": "EX-95"}, {"sequence": "23", "size": "9895455", "documentUrl": "https://www.sec.gov/Archives/edgar/data/18230/000001823014000058/final10k2013pdfwithexhibits.pdf", "description": "10-K PDF WITH EXHIBITS", "type": "10-K"}, {"sequence": "24", "size": "85739", "documentUrl": "https://www.sec.gov/Archives/edgar/data/18230/000001823014000058/a20112012fullyearoperatingpr.jpg", "type": "GRAPHIC"}, {"sequence": "25", "size": "68758", "documentUrl": "https://www.sec.gov/Archives/edgar/data/18230/000001823014000058/a20112012fullyearsalesandrev.jpg", "type": "GRAPHIC"}, {"sequence": "26", "size": "63355", "documentUrl": "https://www.sec.gov/Archives/edgar/data/18230/000001823014000058/catexhibit1312312013chart.jpg", "type": "GRAPHIC"}, {"sequence": "27", "size": "3334", "documentUrl": "https://www.sec.gov/Archives/edgar/data/18230/000001823014000058/catlogo201310k.jpg", "type": "GRAPHIC"}, {"sequence": "28", "size": "84607", "documentUrl": "https://www.sec.gov/Archives/edgar/data/18230/000001823014000058/fourthquarterprofit.jpg", "type": "GRAPHIC"}, {"sequence": "29", "size": "67647", "documentUrl": "https://www.sec.gov/Archives/edgar/data/18230/000001823014000058/fourthquartersales.jpg", "type": "GRAPHIC"}, {"sequence": "30", "size": "67139", "documentUrl": "https://www.sec.gov/Archives/edgar/data/18230/000001823014000058/fullyearprofit.jpg", "type": "GRAPHIC"}, {"sequence": "31", "size": "62931", "documentUrl": "https://www.sec.gov/Archives/edgar/data/18230/000001823014000058/fullyearsales.jpg", "type": "GRAPHIC"}, {"sequence": "\u00a0", "size": "88050247", "documentUrl": "https://www.sec.gov/Archives/edgar/data/18230/000001823014000058/0000018230-14-000058.txt", "description": "Complete submission text file", "type": "\u00a0"}], "periodOfReport": "2013-12-31", "entities": [{"fiscalYearEnd": "1231", "stateOfIncorporation": "DE", "act": "34", "cik": "18230", "fileNo": "001-00768", "irsNo": "370602744", "companyName": "CATERPILLAR INC (Filer)", "type": "10-K", "sic": "3531 Construction Machinery &amp; Equip", "filmNo": "14621711"}], "id": "6f1d0f2fd6530c3c4b5982a565d7b981", "seriesAndClassesContractsInformation": [], "linkToHtml": "https://www.sec.gov/Archives/edgar/data/18230/0000018230-14-000058-index.htm", "linkToXbrl": "", "dataFiles": [{"sequence": "17", "size": "17866122", "documentUrl": "https://www.sec.gov/Archives/edgar/data/18230/000001823014000058/cat-20131231.xml", "description": "XBRL INSTANCE DOCUMENT", "type": "EX-101.INS"}, {"sequence": "18", "size": "186136", "documentUrl": "https://www.sec.gov/Archives/edgar/data/18230/000001823014000058/cat-20131231.xsd", "description": "XBRL TAXONOMY EXTENSION SCHEMA DOCUMENT", "type": "EX-101.SCH"}, {"sequence": "19", "size": "252473", "documentUrl": "https://www.sec.gov/Archives/edgar/data/18230/000001823014000058/cat-20131231_cal.xml", "description": "XBRL TAXONOMY EXTENSION CALCULATION LINKBASE DOCUMENT", "type": "EX-101.CAL"}, {"sequence": "20", "size": "946016", "documentUrl": "https://www.sec.gov/Archives/edgar/data/18230/000001823014000058/cat-20131231_def.xml", "description": "XBRL TAXONOMY EXTENSION DEFINITION LINKBASE DOCUMENT", "type": "EX-101.DEF"}, {"sequence": "21", "size": "2309770", "documentUrl": "https://www.sec.gov/Archives/edgar/data/18230/000001823014000058/cat-20131231_lab.xml", "description": "XBRL TAXONOMY EXTENSION LABEL LINKBASE DOCUMENT", "type": "EX-101.LAB"}, {"sequence": "22", "size": "1310873", "documentUrl": "https://www.sec.gov/Archives/edgar/data/18230/000001823014000058/cat-20131231_pre.xml", "description": "XBRL TAXONOMY EXTENSION PRESENTATION LINKBASE DOCUMENT", "type": "EX-101.PRE"}]}, {"id": "a11cd56eaaba5b23d67f3ad7e9095ee0", "accessionNo": "0000018230-15-000061", "cik": "18230", "ticker": "CAT", "companyName": "CATERPILLAR INC", "companyNameLong": "CATERPILLAR INC (Filer)", "formType": "10-K", "description": "Form 10-K - Annual report [Section 13 and 15(d), not S-K Item 405]", "filedAt": "2015-02-17T17:15:52-05:00", "linkToTxt": "https://www.sec.gov/Archives/edgar/data/18230/000001823015000061/0000018230-15-000061.txt", "linkToHtml": "https://www.sec.gov/Archives/edgar/data/18230/0000018230-15-000061-index.htm", "linkToXbrl": "", "linkToFilingDetails": "https://www.sec.gov/Archives/edgar/data/18230/000001823015000061/cat_10-kx12312014.htm", "entities": [{"companyName": "CATERPILLAR INC (Filer)", "cik": "18230", "irsNo": "370602744", "stateOfIncorporation": "DE", "fiscalYearEnd": "1231", "type": "10-K", "act": "34", "fileNo": "001-00768", "filmNo": "15624323", "sic": "3531 Construction Machinery &amp; Equip"}], "documentFormatFiles": [{"sequence": "1", "description": "10-K", "documentUrl": "https://www.sec.gov/Archives/edgar/data/18230/000001823015000061/cat_10-kx12312014.htm", "type": "10-K", "size": "608240"}, {"sequence": "2", "description": "EX-10.8", "documentUrl": "https://www.sec.gov/Archives/edgar/data/18230/000001823015000061/cat_exx108x12x31x14.htm", "type": "EX-10.8", "size": "34451"}, {"sequence": "3", "description": "EX-10.9", "documentUrl": "https://www.sec.gov/Archives/edgar/data/18230/000001823015000061/cat_exx109x12x31x14.htm", "type": "EX-10.9", "size": "39035"}, {"sequence": "4", "description": "EX-10.10", "documentUrl": "https://www.sec.gov/Archives/edgar/data/18230/000001823015000061/cat_exx1010x12x31x14.htm", "type": "EX-10.10", "size": "36344"}, {"sequence": "5", "description": "EX-10.11", "documentUrl": "https://www.sec.gov/Archives/edgar/data/18230/000001823015000061/cat_exx1011x12x31x14.htm", "type": "EX-10.11", "size": "32272"}, {"sequence": "6", "description": "EX-10.12", "documentUrl": "https://www.sec.gov/Archives/edgar/data/18230/000001823015000061/cat_exx1012x12x31x14.htm", "type": "EX-10.12", "size": "154771"}, {"sequence": "7", "description": "EX-10.13", "documentUrl": "https://www.sec.gov/Archives/edgar/data/18230/000001823015000061/cat_exx1013x12x31x14.htm", "type": "EX-10.13", "size": "128571"}, {"sequence": "8", "description": "EX-10.17", "documentUrl": "https://www.sec.gov/Archives/edgar/data/18230/000001823015000061/cat_exx1017x12x31x14.htm", "type": "EX-10.17", "size": "129423"}, {"sequence": "9", "description": "EX-10.18", "documentUrl": "https://www.sec.gov/Archives/edgar/data/18230/000001823015000061/cat_exx1018x12x31x14.htm", "type": "EX-10.18", "size": "216536"}, {"sequence": "10", "description": "EX-10.19", "documentUrl": "https://www.sec.gov/Archives/edgar/data/18230/000001823015000061/cat_exx1019x12x31x14.htm", "type": "EX-10.19", "size": "106374"}, {"sequence": "11", "description": "EX-10.20", "documentUrl": "https://www.sec.gov/Archives/edgar/data/18230/000001823015000061/cat_exx1020x12x31x14.htm", "type": "EX-10.20", "size": "93891"}, {"sequence": "12", "description": "EX-11", "documentUrl": "https://www.sec.gov/Archives/edgar/data/18230/000001823015000061/cat_exx11x12312014.htm", "type": "EX-11", "size": "30880"}, {"sequence": "13", "description": "EX-12", "documentUrl": "https://www.sec.gov/Archives/edgar/data/18230/000001823015000061/cat_exx12x12312014.htm", "type": "EX-12", "size": "48676"}, {"sequence": "14", "description": "EX-13", "documentUrl": "https://www.sec.gov/Archives/edgar/data/18230/000001823015000061/cat_exx13x12312014.htm", "type": "EX-13", "size": "8912243"}, {"sequence": "15", "description": "EX-14", "documentUrl": "https://www.sec.gov/Archives/edgar/data/18230/000001823015000061/cat_exx14x12x31x14.htm", "type": "EX-14", "size": "84231"}, {"sequence": "16", "description": "EX-21", "documentUrl": "https://www.sec.gov/Archives/edgar/data/18230/000001823015000061/cat_exx2112x31x2014.htm", "type": "EX-21", "size": "396346"}, {"sequence": "17", "description": "EX-23", "documentUrl": "https://www.sec.gov/Archives/edgar/data/18230/000001823015000061/cat_exx23x12312014.htm", "type": "EX-23", "size": "3806"}, {"sequence": "18", "description": "EX-31.1", "documentUrl": "https://www.sec.gov/Archives/edgar/data/18230/000001823015000061/cat_exx311x12312014.htm", "type": "EX-31.1", "size": "16105"}, {"sequence": "19", "description": "EX-31.2", "documentUrl": "https://www.sec.gov/Archives/edgar/data/18230/000001823015000061/cat_exx312x12312014.htm", "type": "EX-31.2", "size": "16016"}, {"sequence": "20", "description": "EX-32", "documentUrl": "https://www.sec.gov/Archives/edgar/data/18230/000001823015000061/cat_exx32x12312014.htm", "type": "EX-32", "size": "12520"}, {"sequence": "21", "description": "EX-95", "documentUrl": "https://www.sec.gov/Archives/edgar/data/18230/000001823015000061/cat_exx95x12312014.htm", "type": "EX-95", "size": "44608"}, {"sequence": "28", "documentUrl": "https://www.sec.gov/Archives/edgar/data/18230/000001823015000061/catexhibit1312312014charta01.jpg", "type": "GRAPHIC", "size": "53059"}, {"sequence": "29", "documentUrl": "https://www.sec.gov/Archives/edgar/data/18230/000001823015000061/catlogo201410k.jpg", "type": "GRAPHIC", "size": "3334"}, {"sequence": "30", "documentUrl": "https://www.sec.gov/Archives/edgar/data/18230/000001823015000061/fourthquarterprofit2014.jpg", "type": "GRAPHIC", "size": "72802"}, {"sequence": "31", "documentUrl": "https://www.sec.gov/Archives/edgar/data/18230/000001823015000061/fourthquartersales2014.jpg", "type": "GRAPHIC", "size": "56066"}, {"sequence": "32", "documentUrl": "https://www.sec.gov/Archives/edgar/data/18230/000001823015000061/fullyearprofit2013.jpg", "type": "GRAPHIC", "size": "67139"}, {"sequence": "33", "documentUrl": "https://www.sec.gov/Archives/edgar/data/18230/000001823015000061/fullyearprofit2014.jpg", "type": "GRAPHIC", "size": "67538"}, {"sequence": "34", "documentUrl": "https://www.sec.gov/Archives/edgar/data/18230/000001823015000061/fullyearsales2013.jpg", "type": "GRAPHIC", "size": "62931"}, {"sequence": "35", "documentUrl": "https://www.sec.gov/Archives/edgar/data/18230/000001823015000061/fullyearsales2014.jpg", "type": "GRAPHIC", "size": "55381"}, {"sequence": "\u00a0", "description": "Complete submission text file", "documentUrl": "https://www.sec.gov/Archives/edgar/data/18230/000001823015000061/0000018230-15-000061.txt", "type": "\u00a0", "size": "78512285"}], "dataFiles": [{"sequence": "22", "description": "XBRL INSTANCE DOCUMENT", "documentUrl": "https://www.sec.gov/Archives/edgar/data/18230/000001823015000061/cat-20141231.xml", "type": "EX-101.INS", "size": "18023230"}, {"sequence": "23", "description": "XBRL TAXONOMY EXTENSION SCHEMA DOCUMENT", "documentUrl": "https://www.sec.gov/Archives/edgar/data/18230/000001823015000061/cat-20141231.xsd", "type": "EX-101.SCH", "size": "175942"}, {"sequence": "24", "description": "XBRL TAXONOMY EXTENSION CALCULATION LINKBASE DOCUMENT", "documentUrl": "https://www.sec.gov/Archives/edgar/data/18230/000001823015000061/cat-20141231_cal.xml", "type": "EX-101.CAL", "size": "234024"}, {"sequence": "25", "description": "XBRL TAXONOMY EXTENSION DEFINITION LINKBASE DOCUMENT", "documentUrl": "https://www.sec.gov/Archives/edgar/data/18230/000001823015000061/cat-20141231_def.xml", "type": "EX-101.DEF", "size": "920476"}, {"sequence": "26", "description": "XBRL TAXONOMY EXTENSION LABEL LINKBASE DOCUMENT", "documentUrl": "https://www.sec.gov/Archives/edgar/data/18230/000001823015000061/cat-20141231_lab.xml", "type": "EX-101.LAB", "size": "2258996"}, {"sequence": "27", "description": "XBRL TAXONOMY EXTENSION PRESENTATION LINKBASE DOCUMENT", "documentUrl": "https://www.sec.gov/Archives/edgar/data/18230/000001823015000061/cat-20141231_pre.xml", "type": "EX-101.PRE", "size": "1278574"}], "seriesAndClassesContractsInformation": [], "periodOfReport": "2014-12-31"}, {"id": "ce33f26894d566fc22954e9f1abfda9f", "accessionNo": "0000018230-16-000410", "cik": "18230", "ticker": "CAT", "companyName": "CATERPILLAR INC", "companyNameLong": "CATERPILLAR INC (Filer)", "formType": "10-K", "description": "Form 10-K - Annual report [Section 13 and 15(d), not S-K Item 405]", "filedAt": "2016-02-16T11:20:14-05:00", "linkToTxt": "https://www.sec.gov/Archives/edgar/data/18230/000001823016000410/0000018230-16-000410.txt", "linkToHtml": "https://www.sec.gov/Archives/edgar/data/18230/0000018230-16-000410-index.htm", "linkToXbrl": "", "linkToFilingDetails": "https://www.sec.gov/Archives/edgar/data/18230/000001823016000410/cat_10-kx12312015.htm", "entities": [{"companyName": "CATERPILLAR INC (Filer)", "cik": "18230", "irsNo": "370602744", "stateOfIncorporation": "DE", "fiscalYearEnd": "1231", "type": "10-K", "act": "34", "fileNo": "001-00768", "filmNo": "161424792", "sic": "3531 Construction Machinery &amp; Equip"}], "documentFormatFiles": [{"sequence": "1", "description": "10-K", "documentUrl": "https://www.sec.gov/Archives/edgar/data/18230/000001823016000410/cat_10-kx12312015.htm", "type": "10-K", "size": "7904374"}, {"sequence": "2", "description": "EXHIBIT 10.5", "documentUrl": "https://www.sec.gov/Archives/edgar/data/18230/000001823016000410/cat_exx105x12312015.htm", "type": "EX-10.5", "size": "7028"}, {"sequence": "3", "description": "EXHIBIT 10.12", "documentUrl": "https://www.sec.gov/Archives/edgar/data/18230/000001823016000410/cat_exx1012x12312015.htm", "type": "EX-10.12", "size": "39029"}, {"sequence": "4", "description": "EXHIBIT 10.14", "documentUrl": "https://www.sec.gov/Archives/edgar/data/18230/000001823016000410/cat_exx1014x12312015.htm", "type": "EX-10.14", "size": "33767"}, {"sequence": "5", "description": "EXHIBIT 10.16", "documentUrl": "https://www.sec.gov/Archives/edgar/data/18230/000001823016000410/cat_exx1016x12312015.htm", "type": "EX-10.16", "size": "6342"}, {"sequence": "6", "description": "EXHIBIT 12", "documentUrl": "https://www.sec.gov/Archives/edgar/data/18230/000001823016000410/cat_exx12x12312015.htm", "type": "EX-12", "size": "48534"}, {"sequence": "7", "description": "EXHIBIT 21", "documentUrl": "https://www.sec.gov/Archives/edgar/data/18230/000001823016000410/cat_exx21x12x31x15.htm", "type": "EX-21", "size": "368808"}, {"sequence": "8", "description": "EXHIBIT 23", "documentUrl": "https://www.sec.gov/Archives/edgar/data/18230/000001823016000410/cat_exx23x12312015.htm", "type": "EX-23", "size": "3649"}, {"sequence": "9", "description": "EXHIBIT 31.1", "documentUrl": "https://www.sec.gov/Archives/edgar/data/18230/000001823016000410/cat_exx311x12312015.htm", "type": "EX-31.1", "size": "16096"}, {"sequence": "10", "description": "EXHIBIT 31.2", "documentUrl": "https://www.sec.gov/Archives/edgar/data/18230/000001823016000410/cat_exx312x12312015.htm", "type": "EX-31.2", "size": "16008"}, {"sequence": "11", "description": "EXHIBIT 32", "documentUrl": "https://www.sec.gov/Archives/edgar/data/18230/000001823016000410/cat_exx32x12312015.htm", "type": "EX-32", "size": "12516"}, {"sequence": "18", "description": "10-K PDF WITH EXHIBITS", "documentUrl": "https://www.sec.gov/Archives/edgar/data/18230/000001823016000410/cat10k2015.pdf", "type": "10-K", "size": "6378127"}, {"sequence": "19", "documentUrl": "https://www.sec.gov/Archives/edgar/data/18230/000001823016000410/a2015performancegraph.jpg", "type": "GRAPHIC", "size": "53462"}, {"sequence": "20", "documentUrl": "https://www.sec.gov/Archives/edgar/data/18230/000001823016000410/catlogo201510k.jpg", "type": "GRAPHIC", "size": "3334"}, {"sequence": "21", "documentUrl": "https://www.sec.gov/Archives/edgar/data/18230/000001823016000410/consopprofit2014q4.jpg", "type": "GRAPHIC", "size": "67538"}, {"sequence": "22", "documentUrl": "https://www.sec.gov/Archives/edgar/data/18230/000001823016000410/consopprofit2015q4.jpg", "type": "GRAPHIC", "size": "70814"}, {"sequence": "23", "documentUrl": "https://www.sec.gov/Archives/edgar/data/18230/000001823016000410/consopprofit2015q4fy.jpg", "type": "GRAPHIC", "size": "58151"}, {"sequence": "24", "documentUrl": "https://www.sec.gov/Archives/edgar/data/18230/000001823016000410/conssalesandrev2014q4fy.jpg", "type": "GRAPHIC", "size": "55381"}, {"sequence": "25", "documentUrl": "https://www.sec.gov/Archives/edgar/data/18230/000001823016000410/conssalesandrev2015q4.jpg", "type": "GRAPHIC", "size": "45121"}, {"sequence": "26", "documentUrl": "https://www.sec.gov/Archives/edgar/data/18230/000001823016000410/conssalesandrev2015q4fy.jpg", "type": "GRAPHIC", "size": "43833"}, {"sequence": "\u00a0", "description": "Complete submission text file", "documentUrl": "https://www.sec.gov/Archives/edgar/data/18230/000001823016000410/0000018230-16-000410.txt", "type": "\u00a0", "size": "52080212"}], "dataFiles": [{"sequence": "12", "description": "XBRL INSTANCE DOCUMENT", "documentUrl": "https://www.sec.gov/Archives/edgar/data/18230/000001823016000410/cat-20151231.xml", "type": "EX-101.INS", "size": "13994629"}, {"sequence": "13", "description": "XBRL TAXONOMY EXTENSION SCHEMA DOCUMENT", "documentUrl": "https://www.sec.gov/Archives/edgar/data/18230/000001823016000410/cat-20151231.xsd", "type": "EX-101.SCH", "size": "144991"}, {"sequence": "14", "description": "XBRL TAXONOMY EXTENSION CALCULATION LINKBASE DOCUMENT", "documentUrl": "https://www.sec.gov/Archives/edgar/data/18230/000001823016000410/cat-20151231_cal.xml", "type": "EX-101.CAL", "size": "222709"}, {"sequence": "15", "description": "XBRL TAXONOMY EXTENSION DEFINITION LINKBASE DOCUMENT", "documentUrl": "https://www.sec.gov/Archives/edgar/data/18230/000001823016000410/cat-20151231_def.xml", "type": "EX-101.DEF", "size": "941440"}, {"sequence": "16", "description": "XBRL TAXONOMY EXTENSION LABEL LINKBASE DOCUMENT", "documentUrl": "https://www.sec.gov/Archives/edgar/data/18230/000001823016000410/cat-20151231_lab.xml", "type": "EX-101.LAB", "size": "2109387"}, {"sequence": "17", "description": "XBRL TAXONOMY EXTENSION PRESENTATION LINKBASE DOCUMENT", "documentUrl": "https://www.sec.gov/Archives/edgar/data/18230/000001823016000410/cat-20151231_pre.xml", "type": "EX-101.PRE", "size": "1240668"}], "seriesAndClassesContractsInformation": [], "periodOfReport": "2015-12-31"}, {"id": "ac96f5b0f1f15657f4e5a13b2b1e611b", "accessionNo": "0000018230-17-000041", "cik": "18230", "ticker": "CAT", "companyName": "CATERPILLAR INC", "companyNameLong": "CATERPILLAR INC (Filer)", "formType": "10-K", "description": "Form 10-K - Annual report [Section 13 and 15(d), not S-K Item 405]", "filedAt": "2017-02-15T13:45:35-05:00", "linkToTxt": "https://www.sec.gov/Archives/edgar/data/18230/000001823017000041/0000018230-17-000041.txt", "linkToHtml": "https://www.sec.gov/Archives/edgar/data/18230/0000018230-17-000041-index.htm", "linkToXbrl": "", "linkToFilingDetails": "https://www.sec.gov/Archives/edgar/data/18230/000001823017000041/cat_10-kx12312016.htm", "entities": [{"companyName": "CATERPILLAR INC (Filer)", "cik": "18230", "irsNo": "370602744", "stateOfIncorporation": "DE", "fiscalYearEnd": "1231", "type": "10-K", "act": "34", "fileNo": "001-00768", "filmNo": "17613998", "sic": "3531 Construction Machinery &amp; Equip"}], "documentFormatFiles": [{"sequence": "1", "description": "10-K", "documentUrl": "https://www.sec.gov/Archives/edgar/data/18230/000001823017000041/cat_10-kx12312016.htm", "type": "10-K", "size": "8498874"}, {"sequence": "2", "description": "EXHIBIT 10.7", "documentUrl": "https://www.sec.gov/Archives/edgar/data/18230/000001823017000041/cat_exx107x12312016.htm", "type": "EX-10.7", "size": "38458"}, {"sequence": "3", "description": "EXHIBIT 10.10", "documentUrl": "https://www.sec.gov/Archives/edgar/data/18230/000001823017000041/cat_exx1010x12312016.htm", "type": "EX-10.10", "size": "35004"}, {"sequence": "4", "description": "EXHIBIT 10.12", "documentUrl": "https://www.sec.gov/Archives/edgar/data/18230/000001823017000041/cat_exx1012x12312016.htm", "type": "EX-10.12", "size": "32413"}, {"sequence": "5", "description": "EXHIBIT 10.15", "documentUrl": "https://www.sec.gov/Archives/edgar/data/18230/000001823017000041/cat_exx1015x12312016.htm", "type": "EX-10.15", "size": "39334"}, {"sequence": "6", "description": "EXHIBIT 10.18", "documentUrl": "https://www.sec.gov/Archives/edgar/data/18230/000001823017000041/cat_exx1018x12312016.htm", "type": "EX-10.18", "size": "33937"}, {"sequence": "7", "description": "EXHIBIT 10.29", "documentUrl": "https://www.sec.gov/Archives/edgar/data/18230/000001823017000041/cat_exx1024x12312016.htm", "type": "EX-10.29", "size": "39953"}, {"sequence": "8", "description": "EXHIBIT 10.30", "documentUrl": "https://www.sec.gov/Archives/edgar/data/18230/000001823017000041/cat_exx1025x12312016.htm", "type": "EX-10.30", "size": "66646"}, {"sequence": "9", "description": "EXHIBIT 12", "documentUrl": "https://www.sec.gov/Archives/edgar/data/18230/000001823017000041/cat_exx12x12312016.htm", "type": "EX-12", "size": "48671"}, {"sequence": "10", "description": "EXHIBIT 21", "documentUrl": "https://www.sec.gov/Archives/edgar/data/18230/000001823017000041/cat_exx21x12312016.htm", "type": "EX-21", "size": "359743"}, {"sequence": "11", "description": "EXHIBIT 23", "documentUrl": "https://www.sec.gov/Archives/edgar/data/18230/000001823017000041/cat_exx23x12312016.htm", "type": "EX-23", "size": "3502"}, {"sequence": "12", "description": "EXHIBIT 31.1", "documentUrl": "https://www.sec.gov/Archives/edgar/data/18230/000001823017000041/cat_exx311x12312016.htm", "type": "EX-31.1", "size": "16422"}, {"sequence": "13", "description": "EXHIBIT 31.2", "documentUrl": "https://www.sec.gov/Archives/edgar/data/18230/000001823017000041/cat_exx312x12312016.htm", "type": "EX-31.2", "size": "16359"}, {"sequence": "14", "description": "EXHIBIT 32", "documentUrl": "https://www.sec.gov/Archives/edgar/data/18230/000001823017000041/catex_32x12312016.htm", "type": "EX-32", "size": "12531"}, {"sequence": "21", "description": "10-K PDF WITH EXHIBITS", "documentUrl": "https://www.sec.gov/Archives/edgar/data/18230/000001823017000041/cat10k2016a01.pdf", "type": "10-K", "size": "7374201"}, {"sequence": "22", "documentUrl": "https://www.sec.gov/Archives/edgar/data/18230/000001823017000041/catlogo201610ka03.jpg", "type": "GRAPHIC", "size": "3334"}, {"sequence": "23", "documentUrl": "https://www.sec.gov/Archives/edgar/data/18230/000001823017000041/cons-opprofit2015fy.jpg", "type": "GRAPHIC", "size": "73829"}, {"sequence": "24", "documentUrl": "https://www.sec.gov/Archives/edgar/data/18230/000001823017000041/cons-opprofit2016q4.jpg", "type": "GRAPHIC", "size": "74071"}, {"sequence": "25", "documentUrl": "https://www.sec.gov/Archives/edgar/data/18230/000001823017000041/cons-opprofit2016q4ytd.jpg", "type": "GRAPHIC", "size": "73114"}, {"sequence": "26", "documentUrl": "https://www.sec.gov/Archives/edgar/data/18230/000001823017000041/cons-salesandrev2015fy.jpg", "type": "GRAPHIC", "size": "43833"}, {"sequence": "27", "documentUrl": "https://www.sec.gov/Archives/edgar/data/18230/000001823017000041/cons-salesandrev2016q4.jpg", "type": "GRAPHIC", "size": "42791"}, {"sequence": "28", "documentUrl": "https://www.sec.gov/Archives/edgar/data/18230/000001823017000041/cons-salesandrev2016q4ytd.jpg", "type": "GRAPHIC", "size": "46900"}, {"sequence": "29", "documentUrl": "https://www.sec.gov/Archives/edgar/data/18230/000001823017000041/stockgraph.jpg", "type": "GRAPHIC", "size": "57091"}, {"sequence": "\u00a0", "description": "Complete submission text file", "documentUrl": "https://www.sec.gov/Archives/edgar/data/18230/000001823017000041/0000018230-17-000041.txt", "type": "\u00a0", "size": "58369704"}], "dataFiles": [{"sequence": "15", "description": "XBRL INSTANCE DOCUMENT", "documentUrl": "https://www.sec.gov/Archives/edgar/data/18230/000001823017000041/cat-20161231.xml", "type": "EX-101.INS", "size": "15934676"}, {"sequence": "16", "description": "XBRL TAXONOMY EXTENSION SCHEMA DOCUMENT", "documentUrl": "https://www.sec.gov/Archives/edgar/data/18230/000001823017000041/cat-20161231.xsd", "type": "EX-101.SCH", "size": "148685"}, {"sequence": "17", "description": "XBRL TAXONOMY EXTENSION CALCULATION LINKBASE DOCUMENT", "documentUrl": "https://www.sec.gov/Archives/edgar/data/18230/000001823017000041/cat-20161231_cal.xml", "type": "EX-101.CAL", "size": "214599"}, {"sequence": "18", "description": "XBRL TAXONOMY EXTENSION DEFINITION LINKBASE DOCUMENT", "documentUrl": "https://www.sec.gov/Archives/edgar/data/18230/000001823017000041/cat-20161231_def.xml", "type": "EX-101.DEF", "size": "1012997"}, {"sequence": "19", "description": "XBRL TAXONOMY EXTENSION LABEL LINKBASE DOCUMENT", "documentUrl": "https://www.sec.gov/Archives/edgar/data/18230/000001823017000041/cat-20161231_lab.xml", "type": "EX-101.LAB", "size": "2148195"}, {"sequence": "20", "description": "XBRL TAXONOMY EXTENSION PRESENTATION LINKBASE DOCUMENT", "documentUrl": "https://www.sec.gov/Archives/edgar/data/18230/000001823017000041/cat-20161231_pre.xml", "type": "EX-101.PRE", "size": "1316996"}], "seriesAndClassesContractsInformation": [], "periodOfReport": "2016-12-31"}, {"id": "641fda13fed7ff38784332b31bfa1d8d", "accessionNo": "0000018230-18-000042", "cik": "18230", "ticker": "CAT", "companyName": "CATERPILLAR INC", "companyNameLong": "CATERPILLAR INC (Filer)", "formType": "10-K", "description": "Form 10-K - Annual report [Section 13 and 15(d), not S-K Item 405]", "filedAt": "2018-02-15T12:14:45-05:00", "linkToTxt": "https://www.sec.gov/Archives/edgar/data/18230/000001823018000042/0000018230-18-000042.txt", "linkToHtml": "https://www.sec.gov/Archives/edgar/data/18230/0000018230-18-000042-index.htm", "linkToXbrl": "", "linkToFilingDetails": "https://www.sec.gov/Archives/edgar/data/18230/000001823018000042/cat_10-kx12312017.htm", "entities": [{"companyName": "CATERPILLAR INC (Filer)", "cik": "18230", "irsNo": "370602744", "stateOfIncorporation": "DE", "fiscalYearEnd": "1231", "type": "10-K", "act": "34", "fileNo": "001-00768", "filmNo": "18616837", "sic": "3531 Construction Machinery &amp; Equip"}], "documentFormatFiles": [{"sequence": "1", "description": "10-K", "documentUrl": "https://www.sec.gov/Archives/edgar/data/18230/000001823018000042/cat_10-kx12312017.htm", "type": "10-K", "size": "8141741"}, {"sequence": "2", "description": "EXHIBIT 10.4", "documentUrl": "https://www.sec.gov/Archives/edgar/data/18230/000001823018000042/cat_exx104x12312017.htm", "type": "EX-10.4", "size": "9759"}, {"sequence": "3", "description": "EXHIBIT 10.22", "documentUrl": "https://www.sec.gov/Archives/edgar/data/18230/000001823018000042/cat_exx1022x12312017.htm", "type": "EX-10.22", "size": "9419"}, {"sequence": "4", "description": "EXHIBIT 10.26", "documentUrl": "https://www.sec.gov/Archives/edgar/data/18230/000001823018000042/cat_exx1026x12312017.htm", "type": "EX-10.26", "size": "9831"}, {"sequence": "5", "description": "EXHIBIT 10.28", "documentUrl": "https://www.sec.gov/Archives/edgar/data/18230/000001823018000042/cat_exx1028x12312017.htm", "type": "EX-10.28", "size": "8559"}, {"sequence": "6", "description": "EXHIBIT 12", "documentUrl": "https://www.sec.gov/Archives/edgar/data/18230/000001823018000042/cat_exx12x12312017.htm", "type": "EX-12", "size": "48565"}, {"sequence": "7", "description": "EXHIBIT 21", "documentUrl": "https://www.sec.gov/Archives/edgar/data/18230/000001823018000042/cat_exx21x12312017.htm", "type": "EX-21", "size": "308107"}, {"sequence": "8", "description": "EXHIBIT 23", "documentUrl": "https://www.sec.gov/Archives/edgar/data/18230/000001823018000042/cat_exx23x12312017.htm", "type": "EX-23", "size": "3445"}, {"sequence": "9", "description": "EXHIBIT 31.1", "documentUrl": "https://www.sec.gov/Archives/edgar/data/18230/000001823018000042/cat_exx311x12312017.htm", "type": "EX-31.1", "size": "16418"}, {"sequence": "10", "description": "EXHIBIT 31.2", "documentUrl": "https://www.sec.gov/Archives/edgar/data/18230/000001823018000042/cat_exx312x12312017.htm", "type": "EX-31.2", "size": "16356"}, {"sequence": "11", "description": "EXHIBIT 32", "documentUrl": "https://www.sec.gov/Archives/edgar/data/18230/000001823018000042/catex_32x12312017.htm", "type": "EX-32", "size": "12526"}, {"sequence": "18", "description": "10-K PDF WITH EXHIBITS", "documentUrl": "https://www.sec.gov/Archives/edgar/data/18230/000001823018000042/finalcat10k2017withexhibits.pdf", "type": "10-K", "size": "6061330"}, {"sequence": "19", "documentUrl": "https://www.sec.gov/Archives/edgar/data/18230/000001823018000042/catlogo201710ka04.jpg", "type": "GRAPHIC", "size": "3334"}, {"sequence": "20", "documentUrl": "https://www.sec.gov/Archives/edgar/data/18230/000001823018000042/cons-opprofit2016q4ytda01.jpg", "type": "GRAPHIC", "size": "73114"}, {"sequence": "21", "documentUrl": "https://www.sec.gov/Archives/edgar/data/18230/000001823018000042/cons-opprofit2017q4a03.jpg", "type": "GRAPHIC", "size": "105277"}, {"sequence": "22", "documentUrl": "https://www.sec.gov/Archives/edgar/data/18230/000001823018000042/cons-opprofit2017q4ytda02.jpg", "type": "GRAPHIC", "size": "111786"}, {"sequence": "23", "documentUrl": "https://www.sec.gov/Archives/edgar/data/18230/000001823018000042/cons-salesandrev2016q4ytda01.jpg", "type": "GRAPHIC", "size": "46900"}, {"sequence": "24", "documentUrl": "https://www.sec.gov/Archives/edgar/data/18230/000001823018000042/cons-salesandrev2017q4a01.jpg", "type": "GRAPHIC", "size": "73205"}, {"sequence": "25", "documentUrl": "https://www.sec.gov/Archives/edgar/data/18230/000001823018000042/cons-salesandrev2017q4ytda01.jpg", "type": "GRAPHIC", "size": "52048"}, {"sequence": "26", "documentUrl": "https://www.sec.gov/Archives/edgar/data/18230/000001823018000042/highlightstable.jpg", "type": "GRAPHIC", "size": "132601"}, {"sequence": "27", "documentUrl": "https://www.sec.gov/Archives/edgar/data/18230/000001823018000042/stockgrapha04.jpg", "type": "GRAPHIC", "size": "78434"}, {"sequence": "\u00a0", "description": "Complete submission text file", "documentUrl": "https://www.sec.gov/Archives/edgar/data/18230/000001823018000042/0000018230-18-000042.txt", "type": "\u00a0", "size": "52636445"}], "dataFiles": [{"sequence": "12", "description": "XBRL INSTANCE DOCUMENT", "documentUrl": "https://www.sec.gov/Archives/edgar/data/18230/000001823018000042/cat-20171231.xml", "type": "EX-101.INS", "size": "14084415"}, {"sequence": "13", "description": "XBRL TAXONOMY EXTENSION SCHEMA DOCUMENT", "documentUrl": "https://www.sec.gov/Archives/edgar/data/18230/000001823018000042/cat-20171231.xsd", "type": "EX-101.SCH", "size": "150552"}, {"sequence": "14", "description": "XBRL TAXONOMY EXTENSION CALCULATION LINKBASE DOCUMENT", "documentUrl": "https://www.sec.gov/Archives/edgar/data/18230/000001823018000042/cat-20171231_cal.xml", "type": "EX-101.CAL", "size": "215774"}, {"sequence": "15", "description": "XBRL TAXONOMY EXTENSION DEFINITION LINKBASE DOCUMENT", "documentUrl": "https://www.sec.gov/Archives/edgar/data/18230/000001823018000042/cat-20171231_def.xml", "type": "EX-101.DEF", "size": "1008526"}, {"sequence": "16", "description": "XBRL TAXONOMY EXTENSION LABEL LINKBASE DOCUMENT", "documentUrl": "https://www.sec.gov/Archives/edgar/data/18230/000001823018000042/cat-20171231_lab.xml", "type": "EX-101.LAB", "size": "2151852"}, {"sequence": "17", "description": "XBRL TAXONOMY EXTENSION PRESENTATION LINKBASE DOCUMENT", "documentUrl": "https://www.sec.gov/Archives/edgar/data/18230/000001823018000042/cat-20171231_pre.xml", "type": "EX-101.PRE", "size": "1316520"}], "seriesAndClassesContractsInformation": [], "periodOfReport": "2017-12-31"}, {"id": "b98a50982bc35a80506064800e2beea4", "accessionNo": "0000018230-19-000034", "cik": "18230", "ticker": "CAT", "companyName": "CATERPILLAR INC", "companyNameLong": "CATERPILLAR INC (Filer)", "formType": "10-K", "description": "Form 10-K - Annual report [Section 13 and 15(d), not S-K Item 405]", "filedAt": "2019-02-14T13:25:13-05:00", "linkToTxt": "https://www.sec.gov/Archives/edgar/data/18230/000001823019000034/0000018230-19-000034.txt", "linkToHtml": "https://www.sec.gov/Archives/edgar/data/18230/0000018230-19-000034-index.htm", "linkToXbrl": "", "linkToFilingDetails": "https://www.sec.gov/Archives/edgar/data/18230/000001823019000034/cat_10-kx12312018.htm", "entities": [{"companyName": "CATERPILLAR INC (Filer)", "cik": "18230", "irsNo": "370602744", "stateOfIncorporation": "DE", "fiscalYearEnd": "1231", "type": "10-K", "act": "34", "fileNo": "001-00768", "filmNo": "19603997", "sic": "3531 Construction Machinery &amp; Equip"}], "documentFormatFiles": [{"sequence": "1", "description": "10-K", "documentUrl": "https://www.sec.gov/Archives/edgar/data/18230/000001823019000034/cat_10-kx12312018.htm", "type": "10-K", "size": "8520502"}, {"sequence": "2", "description": "EXHIBIT 10.10", "documentUrl": "https://www.sec.gov/Archives/edgar/data/18230/000001823019000034/exhibit1010_rsuawardnotice.htm", "type": "EX-10.10", "size": "34749"}, {"sequence": "3", "description": "EXHIBIT 10.19", "documentUrl": "https://www.sec.gov/Archives/edgar/data/18230/000001823019000034/exhibit1019firstamendmentt.htm", "type": "EX-10.19", "size": "5006"}, {"sequence": "4", "description": "EXHIBIT 10.22", "documentUrl": "https://www.sec.gov/Archives/edgar/data/18230/000001823019000034/exhibit1022secondamenmentt.htm", "type": "EX-10.22", "size": "5215"}, {"sequence": "5", "description": "EXHIBIT 10.27", "documentUrl": "https://www.sec.gov/Archives/edgar/data/18230/000001823019000034/exhibit1027secondamendment.htm", "type": "EX-10.27", "size": "5036"}, {"sequence": "6", "description": "EXHIBIT 10.30", "documentUrl": "https://www.sec.gov/Archives/edgar/data/18230/000001823019000034/exhibit1030secondamendment.htm", "type": "EX-10.30", "size": "5099"}, {"sequence": "7", "description": "EXHIBIT 10.38", "documentUrl": "https://www.sec.gov/Archives/edgar/data/18230/000001823019000034/exhibit1038mercersupe340.htm", "type": "EX-10.38", "size": "1869"}, {"sequence": "8", "description": "EXHIBIT 21", "documentUrl": "https://www.sec.gov/Archives/edgar/data/18230/000001823019000034/exhibit21-subsidiaries.htm", "type": "EX-21", "size": "351730"}, {"sequence": "9", "description": "EXHIBIT 23", "documentUrl": "https://www.sec.gov/Archives/edgar/data/18230/000001823019000034/cat_exx23x12312018.htm", "type": "EX-23", "size": "3445"}, {"sequence": "10", "description": "EXHIBIT 31.1", "documentUrl": "https://www.sec.gov/Archives/edgar/data/18230/000001823019000034/cat_exx311x12312018.htm", "type": "EX-31.1", "size": "16422"}, {"sequence": "11", "description": "EXHIBIT 31.2", "documentUrl": "https://www.sec.gov/Archives/edgar/data/18230/000001823019000034/cat_exx312x12312018.htm", "type": "EX-31.2", "size": "16341"}, {"sequence": "12", "description": "EXHIBIT 32", "documentUrl": "https://www.sec.gov/Archives/edgar/data/18230/000001823019000034/catex_32x12312018.htm", "type": "EX-32", "size": "12518"}, {"sequence": "19", "documentUrl": "https://www.sec.gov/Archives/edgar/data/18230/000001823019000034/cons-opprofit2017q4fya01.jpg", "type": "GRAPHIC", "size": "145311"}, {"sequence": "20", "documentUrl": "https://www.sec.gov/Archives/edgar/data/18230/000001823019000034/cons-opprofit2018q4a06.jpg", "type": "GRAPHIC", "size": "112039"}, {"sequence": "21", "documentUrl": "https://www.sec.gov/Archives/edgar/data/18230/000001823019000034/cons-opprofit2018q4fya01.jpg", "type": "GRAPHIC", "size": "124629"}, {"sequence": "22", "documentUrl": "https://www.sec.gov/Archives/edgar/data/18230/000001823019000034/cons-salesandrev2017q4fya01.jpg", "type": "GRAPHIC", "size": "101726"}, {"sequence": "23", "documentUrl": "https://www.sec.gov/Archives/edgar/data/18230/000001823019000034/cons-salesandrev2018q4a02.jpg", "type": "GRAPHIC", "size": "96225"}, {"sequence": "24", "documentUrl": "https://www.sec.gov/Archives/edgar/data/18230/000001823019000034/cons-salesandrev2018q4fya01.jpg", "type": "GRAPHIC", "size": "95834"}, {"sequence": "25", "documentUrl": "https://www.sec.gov/Archives/edgar/data/18230/000001823019000034/stockgraphicitem5.jpg", "type": "GRAPHIC", "size": "66556"}, {"sequence": "26", "description": "CAT LOGO 2018 10K", "documentUrl": "https://www.sec.gov/Archives/edgar/data/18230/000001823019000034/catlogo201810k.jpg", "type": "GRAPHIC", "size": "3334"}, {"sequence": "27", "documentUrl": "https://www.sec.gov/Archives/edgar/data/18230/000001823019000034/exhibit1038mercersupe340001.jpg", "type": "GRAPHIC", "size": "42891"}, {"sequence": "28", "documentUrl": "https://www.sec.gov/Archives/edgar/data/18230/000001823019000034/exhibit1038mercersupe340002.jpg", "type": "GRAPHIC", "size": "117420"}, {"sequence": "29", "documentUrl": "https://www.sec.gov/Archives/edgar/data/18230/000001823019000034/exhibit1038mercersupe340003.jpg", "type": "GRAPHIC", "size": "83248"}, {"sequence": "30", "documentUrl": "https://www.sec.gov/Archives/edgar/data/18230/000001823019000034/exhibit1038mercersupe340004.jpg", "type": "GRAPHIC", "size": "147986"}, {"sequence": "31", "documentUrl": "https://www.sec.gov/Archives/edgar/data/18230/000001823019000034/exhibit1038mercersupe340005.jpg", "type": "GRAPHIC", "size": "99080"}, {"sequence": "32", "description": "10-K PDF WITH EXHIBITS", "documentUrl": "https://www.sec.gov/Archives/edgar/data/18230/000001823019000034/finalcat201810kwithexhibits.pdf", "type": "10-K", "size": "7154015"}, {"sequence": "\u00a0", "description": "Complete submission text file", "documentUrl": "https://www.sec.gov/Archives/edgar/data/18230/000001823019000034/0000018230-19-000034.txt", "type": "\u00a0", "size": "56778859"}], "dataFiles": [{"sequence": "13", "description": "XBRL INSTANCE DOCUMENT", "documentUrl": "https://www.sec.gov/Archives/edgar/data/18230/000001823019000034/cat-20181231.xml", "type": "EX-101.INS", "size": "14631410"}, {"sequence": "14", "description": "XBRL TAXONOMY EXTENSION SCHEMA DOCUMENT", "documentUrl": "https://www.sec.gov/Archives/edgar/data/18230/000001823019000034/cat-20181231.xsd", "type": "EX-101.SCH", "size": "155490"}, {"sequence": "15", "description": "XBRL TAXONOMY EXTENSION CALCULATION LINKBASE DOCUMENT", "documentUrl": "https://www.sec.gov/Archives/edgar/data/18230/000001823019000034/cat-20181231_cal.xml", "type": "EX-101.CAL", "size": "217629"}, {"sequence": "16", "description": "XBRL TAXONOMY EXTENSION DEFINITION LINKBASE DOCUMENT", "documentUrl": "https://www.sec.gov/Archives/edgar/data/18230/000001823019000034/cat-20181231_def.xml", "type": "EX-101.DEF", "size": "1072258"}, {"sequence": "17", "description": "XBRL TAXONOMY EXTENSION LABEL LINKBASE DOCUMENT", "documentUrl": "https://www.sec.gov/Archives/edgar/data/18230/000001823019000034/cat-20181231_lab.xml", "type": "EX-101.LAB", "size": "2183707"}, {"sequence": "18", "description": "XBRL TAXONOMY EXTENSION PRESENTATION LINKBASE DOCUMENT", "documentUrl": "https://www.sec.gov/Archives/edgar/data/18230/000001823019000034/cat-20181231_pre.xml", "type": "EX-101.PRE", "size": "1370577"}], "seriesAndClassesContractsInformation": [], "periodOfReport": "2018-12-31"}]}