{"total": {"value": 10, "relation": "eq"}, "query": {"from": 0, "size": 200}, "filings": [{"ticker": "HD", "formType": "10-K", "accessionNo": "0001193125-10-067178", "cik": "354950", "companyNameLong": "HOME DEPOT INC (Filer)", "companyName": "HOME DEPOT INC", "linkToFilingDetails": "https://www.sec.gov/Archives/edgar/data/354950/000119312510067178/d10k.htm", "description": "Form 10-K - Annual report [Section 13 and 15(d), not S-K Item 405]", "linkToTxt": "https://www.sec.gov/Archives/edgar/data/354950/000119312510067178/0001193125-10-067178.txt", "filedAt": "2010-03-25T16:38:52-04:00", "documentFormatFiles": [{"sequence": "1", "size": "1126047", "documentUrl": "https://www.sec.gov/Archives/edgar/data/354950/000119312510067178/d10k.htm", "description": "FORM 10-K", "type": "10-K"}, {"sequence": "2", "size": "21984", "documentUrl": "https://www.sec.gov/Archives/edgar/data/354950/000119312510067178/dex104.htm", "description": "AMENDMENT #1 TO HOME DEPOT DEFERRED COMPENSATION PLAN", "type": "EX-10.4"}, {"sequence": "3", "size": "7082", "documentUrl": "https://www.sec.gov/Archives/edgar/data/354950/000119312510067178/dex106.htm", "description": "AMENDMENT #1 TO HOME DEPOT 2005M OMNIBUS STOCK INCENTIVE", "type": "EX-10.6"}, {"sequence": "4", "size": "16304", "documentUrl": "https://www.sec.gov/Archives/edgar/data/354950/000119312510067178/dex1035.htm", "description": "MARVIN R. ELLISON EMPLOYMENT ARRANGEMENT", "type": "EX-10.35"}, {"sequence": "5", "size": "28836", "documentUrl": "https://www.sec.gov/Archives/edgar/data/354950/000119312510067178/dex12.htm", "description": "STATEMENT OF COMPUTATION OF RATIO EARNINGS", "type": "EX-12"}, {"sequence": "6", "size": "3783", "documentUrl": "https://www.sec.gov/Archives/edgar/data/354950/000119312510067178/dex21.htm", "description": "LIST OF SUBSIDIARIES OF THE COMPANY", "type": "EX-21"}, {"sequence": "7", "size": "2155", "documentUrl": "https://www.sec.gov/Archives/edgar/data/354950/000119312510067178/dex23.htm", "description": "CONSENT OF KPMG LLP", "type": "EX-23"}, {"sequence": "8", "size": "9195", "documentUrl": "https://www.sec.gov/Archives/edgar/data/354950/000119312510067178/dex311.htm", "description": "CEO CERTIFICATIONS", "type": "EX-31.1"}, {"sequence": "9", "size": "9406", "documentUrl": "https://www.sec.gov/Archives/edgar/data/354950/000119312510067178/dex312.htm", "description": "CFO CERTIFICATIONS", "type": "EX-31.2"}, {"sequence": "10", "size": "3604", "documentUrl": "https://www.sec.gov/Archives/edgar/data/354950/000119312510067178/dex321.htm", "description": "CEO CERTIFICATIONS", "type": "EX-32.1"}, {"sequence": "11", "size": "3867", "documentUrl": "https://www.sec.gov/Archives/edgar/data/354950/000119312510067178/dex322.htm", "description": "CFO CERTIFICATIONS", "type": "EX-32.2"}, {"sequence": "18", "size": "14805", "documentUrl": "https://www.sec.gov/Archives/edgar/data/354950/000119312510067178/g41546g03f11.jpg", "description": "GRAPHIC", "type": "GRAPHIC"}, {"sequence": "19", "size": "39608", "documentUrl": "https://www.sec.gov/Archives/edgar/data/354950/000119312510067178/g41546g94s66.jpg", "description": "GRAPHIC", "type": "GRAPHIC"}, {"sequence": "\u00a0", "size": "3706541", "documentUrl": "https://www.sec.gov/Archives/edgar/data/354950/000119312510067178/0001193125-10-067178.txt", "description": "Complete submission text file", "type": "\u00a0"}], "periodOfReport": "2010-01-31", "entities": [{"fiscalYearEnd": "0128", "stateOfIncorporation": "DE", "act": "34", "cik": "354950", "fileNo": "001-08207", "irsNo": "953261426", "companyName": "HOME DEPOT INC (Filer)", "type": "10-K", "sic": "5211 Retail-Lumber &amp; Other Building Materials Dealers", "filmNo": "10704890"}], "id": "1847bc24cb67953bcc255fb8bf0021a0", "seriesAndClassesContractsInformation": [], "linkToHtml": "https://www.sec.gov/Archives/edgar/data/354950/0001193125-10-067178-index.htm", "linkToXbrl": "", "dataFiles": [{"sequence": "12", "size": "519236", "documentUrl": "https://www.sec.gov/Archives/edgar/data/354950/000119312510067178/hd-20100131.xml", "description": "XBRL INSTANCE DOCUMENT", "type": "EX-101.INS"}, {"sequence": "13", "size": "15063", "documentUrl": "https://www.sec.gov/Archives/edgar/data/354950/000119312510067178/hd-20100131.xsd", "description": "XBRL TAXONOMY EXTENSION SCHEMA", "type": "EX-101.SCH"}, {"sequence": "14", "size": "53023", "documentUrl": "https://www.sec.gov/Archives/edgar/data/354950/000119312510067178/hd-20100131_cal.xml", "description": "XBRL TAXONOMY EXTENSION CALCULATION LINKBASE", "type": "EX-101.CAL"}, {"sequence": "15", "size": "116641", "documentUrl": "https://www.sec.gov/Archives/edgar/data/354950/000119312510067178/hd-20100131_def.xml", "description": "XBRL TAXONOMY EXTENSION DEFINITION LINKBASE", "type": "EX-101.DEF"}, {"sequence": "16", "size": "122622", "documentUrl": "https://www.sec.gov/Archives/edgar/data/354950/000119312510067178/hd-20100131_lab.xml", "description": "XBRL TAXONOMY EXTENSION LABEL LINKBASE", "type": "EX-101.LAB"}, {"sequence": "17", "size": "140886", "documentUrl": "https://www.sec.gov/Archives/edgar/data/354950/000119312510067178/hd-20100131_pre.xml", "description": "XBRL TAXONOMY EXTENSION PRESENTATION LINKBASE", "type": "EX-101.PRE"}]}, {"ticker": "HD", "formType": "10-K", "accessionNo": "0001193125-11-076501", "cik": "354950", "companyNameLong": "HOME DEPOT INC (Filer)", "companyName": "HOME DEPOT INC", "linkToFilingDetails": "https://www.sec.gov/Archives/edgar/data/354950/000119312511076501/d10k.htm", "description": "Form 10-K - Annual report [Section 13 and 15(d), not S-K Item 405]", "linkToTxt": "https://www.sec.gov/Archives/edgar/data/354950/000119312511076501/0001193125-11-076501.txt", "filedAt": "2011-03-24T16:21:02-04:00", "documentFormatFiles": [{"sequence": "1", "size": "1185116", "documentUrl": "https://www.sec.gov/Archives/edgar/data/354950/000119312511076501/d10k.htm", "description": "FORM 10-K", "type": "10-K"}, {"sequence": "2", "size": "13446", "documentUrl": "https://www.sec.gov/Archives/edgar/data/354950/000119312511076501/dex102.htm", "description": "FORM OF EMPLOYMENT DEATH BENEFIT AGREEMENT", "type": "EX-10.2"}, {"sequence": "3", "size": "27617", "documentUrl": "https://www.sec.gov/Archives/edgar/data/354950/000119312511076501/dex1034.htm", "description": "AGREEMENT & RELEASE", "type": "EX-10.34"}, {"sequence": "4", "size": "37718", "documentUrl": "https://www.sec.gov/Archives/edgar/data/354950/000119312511076501/dex1036.htm", "description": "EMPLOYMENT ARRANGEMENT", "type": "EX-10.36"}, {"sequence": "5", "size": "29109", "documentUrl": "https://www.sec.gov/Archives/edgar/data/354950/000119312511076501/dex12.htm", "description": "STATEMENT OF COMPUTATION OF RATIO OF EARNINGS TO FIXED CHARGES", "type": "EX-12"}, {"sequence": "6", "size": "2218", "documentUrl": "https://www.sec.gov/Archives/edgar/data/354950/000119312511076501/dex23.htm", "description": "CONSENT OF INDEPENDENT REGISTERED PUBLIC ACCOUNTING FIRM", "type": "EX-23"}, {"sequence": "7", "size": "9305", "documentUrl": "https://www.sec.gov/Archives/edgar/data/354950/000119312511076501/dex311.htm", "description": "SECTION 302 CERTIFICATION OF THE CEO", "type": "EX-31.1"}, {"sequence": "8", "size": "9422", "documentUrl": "https://www.sec.gov/Archives/edgar/data/354950/000119312511076501/dex312.htm", "description": "SECTION 302 CERTIFICATION OF THE CFO", "type": "EX-31.2"}, {"sequence": "9", "size": "3657", "documentUrl": "https://www.sec.gov/Archives/edgar/data/354950/000119312511076501/dex321.htm", "description": "SECTION 906 CERTIFICATION OF THE CEO", "type": "EX-32.1"}, {"sequence": "10", "size": "3752", "documentUrl": "https://www.sec.gov/Archives/edgar/data/354950/000119312511076501/dex322.htm", "description": "SECTION 906 CERTIFICATION OF THE CFO", "type": "EX-32.2"}, {"sequence": "17", "size": "17043", "documentUrl": "https://www.sec.gov/Archives/edgar/data/354950/000119312511076501/g133833ex10_36pg01.jpg", "description": "GRAPHIC", "type": "GRAPHIC"}, {"sequence": "18", "size": "35124", "documentUrl": "https://www.sec.gov/Archives/edgar/data/354950/000119312511076501/g133833g48q88.jpg", "description": "GRAPHIC", "type": "GRAPHIC"}, {"sequence": "\u00a0", "size": "8714969", "documentUrl": "https://www.sec.gov/Archives/edgar/data/354950/000119312511076501/0001193125-11-076501.txt", "description": "Complete submission text file", "type": "\u00a0"}], "entities": [{"fiscalYearEnd": "0128", "stateOfIncorporation": "DE", "act": "34", "cik": "0000354950", "fileNo": "001-08207", "irsNo": "953261426", "companyName": "HOME DEPOT INC (Filer)", "type": "10-K", "sic": "5211 Retail-Lumber &amp; Other Building Materials Dealers", "filmNo": "11709624"}], "id": "4f338f9d726884aa3f95027a2adae7f8", "seriesAndClassesContractsInformation": [], "linkToHtml": "https://www.sec.gov/Archives/edgar/data/354950/0001193125-11-076501-index.htm", "linkToXbrl": "", "dataFiles": [{"sequence": "11", "size": "1142212", "documentUrl": "https://www.sec.gov/Archives/edgar/data/354950/000119312511076501/hd-20110130.xml", "description": "XBRL INSTANCE DOCUMENT", "type": "EX-101.INS"}, {"sequence": "12", "size": "57229", "documentUrl": "https://www.sec.gov/Archives/edgar/data/354950/000119312511076501/hd-20110130.xsd", "description": "XBRL TAXONOMY EXTENSION SCHEMA", "type": "EX-101.SCH"}, {"sequence": "13", "size": "85544", "documentUrl": "https://www.sec.gov/Archives/edgar/data/354950/000119312511076501/hd-20110130_cal.xml", "description": "XBRL TAXONOMY EXTENSION CALCULATION LINKBASE", "type": "EX-101.CAL"}, {"sequence": "14", "size": "170272", "documentUrl": "https://www.sec.gov/Archives/edgar/data/354950/000119312511076501/hd-20110130_def.xml", "description": "XBRL TAXONOMY EXTENSION DEFINITION LINKBASE", "type": "EX-101.DEF"}, {"sequence": "15", "size": "482358", "documentUrl": "https://www.sec.gov/Archives/edgar/data/354950/000119312511076501/hd-20110130_lab.xml", "description": "XBRL TAXONOMY EXTENSION LABEL LINKBASE", "type": "EX-101.LAB"}, {"sequence": "16", "size": "348956", "documentUrl": "https://www.sec.gov/Archives/edgar/data/354950/000119312511076501/hd-20110130_pre.xml", "description": "XBRL TAXONOMY EXTENSION PRESENTATION LINKBASE", "type": "EX-101.PRE"}]}, {"ticker": "HD", "formType": "10-K", "accessionNo": "0000354950-12-000003", "cik": "354950", "companyNameLong": "HOME DEPOT INC (Filer)", "companyName": "HOME DEPOT INC", "linkToFilingDetails": "https://www.sec.gov/Archives/edgar/data/354950/000035495012000003/hd-1292012x10xk.htm", "description": "Form 10-K - Annual report [Section 13 and 15(d), not S-K Item 405]", "linkToTxt": "https://www.sec.gov/Archives/edgar/data/354950/000035495012000003/0000354950-12-000003.txt", "filedAt": "2012-03-22T16:14:41-04:00", "documentFormatFiles": [{"sequence": "1", "size": "1862103", "documentUrl": "https://www.sec.gov/Archives/edgar/data/354950/000035495012000003/hd-1292012x10xk.htm", "description": "FORM 10-K", "type": "10-K"}, {"sequence": "2", "size": "49962", "documentUrl": "https://www.sec.gov/Archives/edgar/data/354950/000035495012000003/hd-1292012xexx12.htm", "description": "STATEMENT OF COMPUTATION OF RATIO OF EARNINGS TO FIXED CHARGES", "type": "EX-12"}, {"sequence": "3", "size": "3381", "documentUrl": "https://www.sec.gov/Archives/edgar/data/354950/000035495012000003/hd-1292012xexx23.htm", "description": "CONSENT OF INDEPENDENT REGISTERED PUBLIC ACCOUNTING FIRM", "type": "EX-23"}, {"sequence": "4", "size": "12770", "documentUrl": "https://www.sec.gov/Archives/edgar/data/354950/000035495012000003/hd-1292012xexx311.htm", "description": "SECTION 302 CERTIFICATION OF THE CEO", "type": "EX-31.1"}, {"sequence": "5", "size": "13111", "documentUrl": "https://www.sec.gov/Archives/edgar/data/354950/000035495012000003/hd-1292012xexx312.htm", "description": "SECTION 302 CERTIFICATION OF THE CFO", "type": "EX-31.2"}, {"sequence": "6", "size": "5942", "documentUrl": "https://www.sec.gov/Archives/edgar/data/354950/000035495012000003/hd-1292012xexx321.htm", "description": "SECTION 906 CERTIFICATION OF THE CEO", "type": "EX-32.1"}, {"sequence": "7", "size": "5933", "documentUrl": "https://www.sec.gov/Archives/edgar/data/354950/000035495012000003/hd-1292012xexx322.htm", "description": "SECTION 906 CERTIFICATION OF THE CFO", "type": "EX-32.2"}, {"sequence": "14", "size": "161017", "documentUrl": "https://www.sec.gov/Archives/edgar/data/354950/000035495012000003/stockperformancegraph.jpg", "description": "STOCK PERFORMANCE GRAPH", "type": "GRAPHIC"}, {"sequence": "\u00a0", "size": "10720803", "documentUrl": "https://www.sec.gov/Archives/edgar/data/354950/000035495012000003/0000354950-12-000003.txt", "description": "Complete submission text file", "type": "\u00a0"}], "entities": [{"fiscalYearEnd": "0129", "stateOfIncorporation": "DE", "act": "34", "cik": "0000354950", "fileNo": "001-08207", "irsNo": "953261426", "companyName": "HOME DEPOT INC (Filer)", "type": "10-K", "sic": "5211 Retail-Lumber &amp; Other Building Materials Dealers", "filmNo": "12709452"}], "id": "f85cc6cd43bd8b1ac938f879d6a898ee", "seriesAndClassesContractsInformation": [], "linkToHtml": "https://www.sec.gov/Archives/edgar/data/354950/0000354950-12-000003-index.htm", "linkToXbrl": "", "dataFiles": [{"sequence": "8", "size": "1623063", "documentUrl": "https://www.sec.gov/Archives/edgar/data/354950/000035495012000003/hd-20120129.xml", "description": "XBRL INSTANCE DOCUMENT", "type": "EX-101.INS"}, {"sequence": "9", "size": "56922", "documentUrl": "https://www.sec.gov/Archives/edgar/data/354950/000035495012000003/hd-20120129.xsd", "description": "XBRL TAXONOMY EXTENSION SCHEMA DOCUMENT", "type": "EX-101.SCH"}, {"sequence": "10", "size": "103905", "documentUrl": "https://www.sec.gov/Archives/edgar/data/354950/000035495012000003/hd-20120129_cal.xml", "description": "XBRL TAXONOMY EXTENSION CALCULATION LINKBASE DOCUMENT", "type": "EX-101.CAL"}, {"sequence": "11", "size": "308617", "documentUrl": "https://www.sec.gov/Archives/edgar/data/354950/000035495012000003/hd-20120129_def.xml", "description": "XBRL TAXONOMY EXTENSION DEFINITION LINKBASE DOCUMENT", "type": "EX-101.DEF"}, {"sequence": "12", "size": "829928", "documentUrl": "https://www.sec.gov/Archives/edgar/data/354950/000035495012000003/hd-20120129_lab.xml", "description": "XBRL TAXONOMY EXTENSION LABEL LINKBASE DOCUMENT", "type": "EX-101.LAB"}, {"sequence": "13", "size": "449007", "documentUrl": "https://www.sec.gov/Archives/edgar/data/354950/000035495012000003/hd-20120129_pre.xml", "description": "XBRL TAXONOMY EXTENSION PRESENTATION LINKBASE DOCUMENT", "type": "EX-101.PRE"}]}, {"ticker": "HD", "formType": "10-K", "accessionNo": "0000354950-13-000008", "cik": "354950", "companyNameLong": "HOME DEPOT INC (Filer)", "companyName": "HOME DEPOT INC", "linkToFilingDetails": "https://www.sec.gov/Archives/edgar/data/354950/000035495013000008/hd-232013x10xk.htm", "description": "Form 10-K - Annual report [Section 13 and 15(d), not S-K Item 405]", "linkToTxt": "https://www.sec.gov/Archives/edgar/data/354950/000035495013000008/0000354950-13-000008.txt", "filedAt": "2013-03-28T16:22:36-04:00", "documentFormatFiles": [{"sequence": "1", "size": "1716823", "documentUrl": "https://www.sec.gov/Archives/edgar/data/354950/000035495013000008/hd-232013x10xk.htm", "description": "10-K", "type": "10-K"}, {"sequence": "2", "size": "18793", "documentUrl": "https://www.sec.gov/Archives/edgar/data/354950/000035495013000008/hd-232013xexx102.htm", "description": "FORM OF EXECUTIVE EMPLOYMENT DEATH BENEFIT AGREEMENT", "type": "EX-10.2"}, {"sequence": "3", "size": "9527", "documentUrl": "https://www.sec.gov/Archives/edgar/data/354950/000035495013000008/hd-232013xexx1022.htm", "description": "AMENDMENT TO EMPLOYMENT ARRANGEMENT", "type": "EX-10.22"}, {"sequence": "4", "size": "49979", "documentUrl": "https://www.sec.gov/Archives/edgar/data/354950/000035495013000008/hd-232013xexx12.htm", "description": "STATEMENT OF COMPUTATION OF RATIO OF EARNINGS TO FIXED CHARGES", "type": "EX-12"}, {"sequence": "5", "size": "11899", "documentUrl": "https://www.sec.gov/Archives/edgar/data/354950/000035495013000008/hd-232013xexx21.htm", "description": "LIST OF SUBSIDIARIES OF THE COMPANY", "type": "EX-21"}, {"sequence": "6", "size": "4166", "documentUrl": "https://www.sec.gov/Archives/edgar/data/354950/000035495013000008/hd-232013xexx23.htm", "description": "CONSENT OF INDEPENDENT REGISTERED PUBLIC ACCOUNTING FIRM", "type": "EX-23"}, {"sequence": "7", "size": "12756", "documentUrl": "https://www.sec.gov/Archives/edgar/data/354950/000035495013000008/hd-232013xexx311.htm", "description": "CERTIFICATION OF THE CEO", "type": "EX-31.1"}, {"sequence": "8", "size": "13097", "documentUrl": "https://www.sec.gov/Archives/edgar/data/354950/000035495013000008/hd-232013xexx312.htm", "description": "CERTIFICATION OF THE CFO", "type": "EX-31.2"}, {"sequence": "9", "size": "5940", "documentUrl": "https://www.sec.gov/Archives/edgar/data/354950/000035495013000008/hd-232013xexx321.htm", "description": "SECTION 906 CERTIFICATION OF THE CEO", "type": "EX-32.1"}, {"sequence": "10", "size": "5875", "documentUrl": "https://www.sec.gov/Archives/edgar/data/354950/000035495013000008/hd-232013xexx322.htm", "description": "SECTION 906 CERTIFICATION OF THE CFO", "type": "EX-32.2"}, {"sequence": "17", "size": "7725", "documentUrl": "https://www.sec.gov/Archives/edgar/data/354950/000035495013000008/hdlogo.jpg", "type": "GRAPHIC"}, {"sequence": "18", "size": "132061", "documentUrl": "https://www.sec.gov/Archives/edgar/data/354950/000035495013000008/stockperformancegraphfinal.jpg", "type": "GRAPHIC"}, {"sequence": "\u00a0", "size": "9744169", "documentUrl": "https://www.sec.gov/Archives/edgar/data/354950/000035495013000008/0000354950-13-000008.txt", "description": "Complete submission text file", "type": "\u00a0"}], "periodOfReport": "2013-02-03", "entities": [{"fiscalYearEnd": "0129", "stateOfIncorporation": "DE", "act": "34", "cik": "354950", "fileNo": "001-08207", "irsNo": "953261426", "companyName": "HOME DEPOT INC (Filer)", "type": "10-K", "sic": "5211 Retail-Lumber &amp; Other Building Materials Dealers", "filmNo": "13724257"}], "id": "4884e53535bbf9cd9ec0b1bdd70804e2", "seriesAndClassesContractsInformation": [], "linkToHtml": "https://www.sec.gov/Archives/edgar/data/354950/0000354950-13-000008-index.htm", "linkToXbrl": "", "dataFiles": [{"sequence": "11", "size": "1392745", "documentUrl": "https://www.sec.gov/Archives/edgar/data/354950/000035495013000008/hd-20130203.xml", "description": "XBRL INSTANCE DOCUMENT", "type": "EX-101.INS"}, {"sequence": "12", "size": "47890", "documentUrl": "https://www.sec.gov/Archives/edgar/data/354950/000035495013000008/hd-20130203.xsd", "description": "XBRL TAXONOMY EXTENSION SCHEMA DOCUMENT", "type": "EX-101.SCH"}, {"sequence": "13", "size": "96828", "documentUrl": "https://www.sec.gov/Archives/edgar/data/354950/000035495013000008/hd-20130203_cal.xml", "description": "XBRL TAXONOMY EXTENSION CALCULATION LINKBASE DOCUMENT", "type": "EX-101.CAL"}, {"sequence": "14", "size": "284449", "documentUrl": "https://www.sec.gov/Archives/edgar/data/354950/000035495013000008/hd-20130203_def.xml", "description": "XBRL TAXONOMY EXTENSION DEFINITION LINKBASE DOCUMENT", "type": "EX-101.DEF"}, {"sequence": "15", "size": "769291", "documentUrl": "https://www.sec.gov/Archives/edgar/data/354950/000035495013000008/hd-20130203_lab.xml", "description": "XBRL TAXONOMY EXTENSION LABEL LINKBASE DOCUMENT", "type": "EX-101.LAB"}, {"sequence": "16", "size": "428284", "documentUrl": "https://www.sec.gov/Archives/edgar/data/354950/000035495013000008/hd-20130203_pre.xml", "description": "XBRL TAXONOMY EXTENSION PRESENTATION LINKBASE DOCUMENT", "type": "EX-101.PRE"}]}, {"ticker": "HD", "formType": "10-K", "accessionNo": "0000354950-14-000008", "cik": "354950", "companyNameLong": "HOME DEPOT INC (Filer)", "companyName": "HOME DEPOT INC", "linkToFilingDetails": "https://www.sec.gov/Archives/edgar/data/354950/000035495014000008/hd-222014x10xk.htm", "description": "Form 10-K - Annual report [Section 13 and 15(d), not S-K Item 405]", "linkToTxt": "https://www.sec.gov/Archives/edgar/data/354950/000035495014000008/0000354950-14-000008.txt", "filedAt": "2014-03-27T16:14:17-04:00", "documentFormatFiles": [{"sequence": "1", "size": "1754528", "documentUrl": "https://www.sec.gov/Archives/edgar/data/354950/000035495014000008/hd-222014x10xk.htm", "description": "10-K", "type": "10-K"}, {"sequence": "2", "size": "20345", "documentUrl": "https://www.sec.gov/Archives/edgar/data/354950/000035495014000008/hd-222014xexx108.htm", "description": "AMENDMENT NO. 1 TO THD FUTUREBUILDER RESTORATION PLAN", "type": "EX-10.8"}, {"sequence": "3", "size": "61270", "documentUrl": "https://www.sec.gov/Archives/edgar/data/354950/000035495014000008/hd-222014xexx1010.htm", "description": "AMENDED AND RESTATED MANAGEMENT INCENTIVE PLAN", "type": "EX-10.10"}, {"sequence": "4", "size": "49553", "documentUrl": "https://www.sec.gov/Archives/edgar/data/354950/000035495014000008/hd-222014xexx12.htm", "description": "STATEMENT OF COMPUTATION OF RATIO OF EARNINGS TO FIXED CHARGES", "type": "EX-12"}, {"sequence": "5", "size": "4166", "documentUrl": "https://www.sec.gov/Archives/edgar/data/354950/000035495014000008/hd-222014xexx23.htm", "description": "CONSENT OF INDEPENDENT REGISTERED PUBLIC ACCOUNTING FIRM", "type": "EX-23"}, {"sequence": "6", "size": "12756", "documentUrl": "https://www.sec.gov/Archives/edgar/data/354950/000035495014000008/hd-222014xexx311.htm", "description": "CERTIFICATION OF THE CEO", "type": "EX-31.1"}, {"sequence": "7", "size": "13103", "documentUrl": "https://www.sec.gov/Archives/edgar/data/354950/000035495014000008/hd-222014xexx312.htm", "description": "CERTIFICATION OF THE CFO", "type": "EX-31.2"}, {"sequence": "8", "size": "5940", "documentUrl": "https://www.sec.gov/Archives/edgar/data/354950/000035495014000008/hd-222014xexx321.htm", "description": "SECTION 906 CERTIFICATION OF THE CEO", "type": "EX-32.1"}, {"sequence": "9", "size": "5880", "documentUrl": "https://www.sec.gov/Archives/edgar/data/354950/000035495014000008/hd-222014xexx322.htm", "description": "SECTION 906 CERTIFICATION OF THE CFO", "type": "EX-32.2"}, {"sequence": "16", "size": "74030", "documentUrl": "https://www.sec.gov/Archives/edgar/data/354950/000035495014000008/hd-222014x1_chartx19303.jpg", "type": "GRAPHIC"}, {"sequence": "\u00a0", "size": "10150336", "documentUrl": "https://www.sec.gov/Archives/edgar/data/354950/000035495014000008/0000354950-14-000008.txt", "description": "Complete submission text file", "type": "\u00a0"}], "periodOfReport": "2014-02-02", "entities": [{"fiscalYearEnd": "0129", "stateOfIncorporation": "DE", "act": "34", "cik": "354950", "fileNo": "001-08207", "irsNo": "953261426", "companyName": "HOME DEPOT INC (Filer)", "type": "10-K", "sic": "5211 Retail-Lumber &amp; Other Building Materials Dealers", "filmNo": "14721781"}], "id": "4cb086a53eec9e1d8791e41ba87c000a", "seriesAndClassesContractsInformation": [], "linkToHtml": "https://www.sec.gov/Archives/edgar/data/354950/0000354950-14-000008-index.htm", "linkToXbrl": "", "dataFiles": [{"sequence": "10", "size": "1548822", "documentUrl": "https://www.sec.gov/Archives/edgar/data/354950/000035495014000008/hd-20140202.xml", "description": "XBRL INSTANCE DOCUMENT", "type": "EX-101.INS"}, {"sequence": "11", "size": "49793", "documentUrl": "https://www.sec.gov/Archives/edgar/data/354950/000035495014000008/hd-20140202.xsd", "description": "XBRL TAXONOMY EXTENSION SCHEMA DOCUMENT", "type": "EX-101.SCH"}, {"sequence": "12", "size": "96103", "documentUrl": "https://www.sec.gov/Archives/edgar/data/354950/000035495014000008/hd-20140202_cal.xml", "description": "XBRL TAXONOMY EXTENSION CALCULATION LINKBASE DOCUMENT", "type": "EX-101.CAL"}, {"sequence": "13", "size": "211069", "documentUrl": "https://www.sec.gov/Archives/edgar/data/354950/000035495014000008/hd-20140202_def.xml", "description": "XBRL TAXONOMY EXTENSION DEFINITION LINKBASE DOCUMENT", "type": "EX-101.DEF"}, {"sequence": "14", "size": "776740", "documentUrl": "https://www.sec.gov/Archives/edgar/data/354950/000035495014000008/hd-20140202_lab.xml", "description": "XBRL TAXONOMY EXTENSION LABEL LINKBASE DOCUMENT", "type": "EX-101.LAB"}, {"sequence": "15", "size": "419635", "documentUrl": "https://www.sec.gov/Archives/edgar/data/354950/000035495014000008/hd-20140202_pre.xml", "description": "XBRL TAXONOMY EXTENSION PRESENTATION LINKBASE DOCUMENT", "type": "EX-101.PRE"}]}, {"id": "a00477866d36db676d01fa58d85d6e8c", "accessionNo": "0000354950-15-000008", "cik": "354950", "ticker": "HD", "companyName": "HOME DEPOT INC", "companyNameLong": "HOME DEPOT INC (Filer)", "formType": "10-K", "description": "Form 10-K - Annual report [Section 13 and 15(d), not S-K Item 405]", "filedAt": "2015-03-26T16:03:43-04:00", "linkToTxt": "https://www.sec.gov/Archives/edgar/data/354950/000035495015000008/0000354950-15-000008.txt", "linkToHtml": "https://www.sec.gov/Archives/edgar/data/354950/0000354950-15-000008-index.htm", "linkToXbrl": "", "linkToFilingDetails": "https://www.sec.gov/Archives/edgar/data/354950/000035495015000008/hd-212015x10xk.htm", "entities": [{"companyName": "HOME DEPOT INC (Filer)", "cik": "354950", "irsNo": "953261426", "stateOfIncorporation": "DE", "fiscalYearEnd": "0201", "type": "10-K", "act": "34", "fileNo": "001-08207", "filmNo": "15727728", "sic": "5211 Retail-Lumber &amp; Other Building Materials Dealers"}], "documentFormatFiles": [{"sequence": "1", "description": "10-K", "documentUrl": "https://www.sec.gov/Archives/edgar/data/354950/000035495015000008/hd-212015x10xk.htm", "type": "10-K", "size": "1795903"}, {"sequence": "2", "description": "EMPLOYMENT ARRANGEMENT BETWEEN MARK Q. HOLIFIELD AND THE HOME DEPOT, INC.", "documentUrl": "https://www.sec.gov/Archives/edgar/data/354950/000035495015000008/hd-212015xexx1030.htm", "type": "EX-10.30", "size": "26781"}, {"sequence": "3", "description": "EMPLOYMENT ARRANGEMENT BETWEEN TIMOTHY M. CROW AND THE HOME DEPOT, INC.", "documentUrl": "https://www.sec.gov/Archives/edgar/data/354950/000035495015000008/hd-212015xexx1031.htm", "type": "EX-10.31", "size": "21357"}, {"sequence": "4", "description": "STATEMENT OF COMPUTATION OF RATIO OF EARNINGS TO FIXED CHARGES", "documentUrl": "https://www.sec.gov/Archives/edgar/data/354950/000035495015000008/hd-212015xexx12.htm", "type": "EX-12", "size": "49518"}, {"sequence": "5", "description": "LIST OF SUBSIDIARIES OF THE COMPANY", "documentUrl": "https://www.sec.gov/Archives/edgar/data/354950/000035495015000008/hd-212015xexx21.htm", "type": "EX-21", "size": "12959"}, {"sequence": "6", "description": "CONSENT OF INDEPENDENT REGISTERED PUBLIC ACCOUNTING FIRM", "documentUrl": "https://www.sec.gov/Archives/edgar/data/354950/000035495015000008/hd-212015xexx23.htm", "type": "EX-23", "size": "4128"}, {"sequence": "7", "description": "CERTIFICATION OF THE CEO", "documentUrl": "https://www.sec.gov/Archives/edgar/data/354950/000035495015000008/hd-212015xexx311.htm", "type": "EX-31.1", "size": "12702"}, {"sequence": "8", "description": "CERTIFICATION OF THE CFO", "documentUrl": "https://www.sec.gov/Archives/edgar/data/354950/000035495015000008/hd-212015xexx312.htm", "type": "EX-31.2", "size": "13065"}, {"sequence": "9", "description": "SECTION 906 CERTIFICATION OF THE CEO", "documentUrl": "https://www.sec.gov/Archives/edgar/data/354950/000035495015000008/hd-212015xexx321.htm", "type": "EX-32.1", "size": "5916"}, {"sequence": "10", "description": "SECTION 906 CERTIFICATION OF THE CFO", "documentUrl": "https://www.sec.gov/Archives/edgar/data/354950/000035495015000008/hd-212015xexx322.htm", "type": "EX-32.2", "size": "5862"}, {"sequence": "17", "description": "STOCK PERFORMANCE GRAPH", "documentUrl": "https://www.sec.gov/Archives/edgar/data/354950/000035495015000008/hd-222014x1_chartx19303a02.jpg", "type": "GRAPHIC", "size": "73442"}, {"sequence": "\u00a0", "description": "Complete submission text file", "documentUrl": "https://www.sec.gov/Archives/edgar/data/354950/000035495015000008/0000354950-15-000008.txt", "type": "\u00a0", "size": "11290968"}], "dataFiles": [{"sequence": "11", "description": "XBRL INSTANCE DOCUMENT", "documentUrl": "https://www.sec.gov/Archives/edgar/data/354950/000035495015000008/hd-20150201.xml", "type": "EX-101.INS", "size": "1594619"}, {"sequence": "12", "description": "XBRL TAXONOMY EXTENSION SCHEMA DOCUMENT", "documentUrl": "https://www.sec.gov/Archives/edgar/data/354950/000035495015000008/hd-20150201.xsd", "type": "EX-101.SCH", "size": "55371"}, {"sequence": "13", "description": "XBRL TAXONOMY EXTENSION CALCULATION LINKBASE DOCUMENT", "documentUrl": "https://www.sec.gov/Archives/edgar/data/354950/000035495015000008/hd-20150201_cal.xml", "type": "EX-101.CAL", "size": "99522"}, {"sequence": "14", "description": "XBRL TAXONOMY EXTENSION DEFINITION LINKBASE DOCUMENT", "documentUrl": "https://www.sec.gov/Archives/edgar/data/354950/000035495015000008/hd-20150201_def.xml", "type": "EX-101.DEF", "size": "271845"}, {"sequence": "15", "description": "XBRL TAXONOMY EXTENSION LABEL LINKBASE DOCUMENT", "documentUrl": "https://www.sec.gov/Archives/edgar/data/354950/000035495015000008/hd-20150201_lab.xml", "type": "EX-101.LAB", "size": "867915"}, {"sequence": "16", "description": "XBRL TAXONOMY EXTENSION PRESENTATION LINKBASE DOCUMENT", "documentUrl": "https://www.sec.gov/Archives/edgar/data/354950/000035495015000008/hd-20150201_pre.xml", "type": "EX-101.PRE", "size": "478846"}], "seriesAndClassesContractsInformation": [], "periodOfReport": "2015-02-01"}, {"id": "619ddf2b28d851f7dd24aee15912bfa9", "accessionNo": "0000354950-16-000060", "cik": "354950", "ticker": "HD", "companyName": "HOME DEPOT INC", "companyNameLong": "HOME DEPOT INC (Filer)", "formType": "10-K", "description": "Form 10-K - Annual report [Section 13 and 15(d), not S-K Item 405]", "filedAt": "2016-03-24T16:05:36-04:00", "linkToTxt": "https://www.sec.gov/Archives/edgar/data/354950/000035495016000060/0000354950-16-000060.txt", "linkToHtml": "https://www.sec.gov/Archives/edgar/data/354950/0000354950-16-000060-index.htm", "linkToXbrl": "", "linkToFilingDetails": "https://www.sec.gov/Archives/edgar/data/354950/000035495016000060/hd-1312016x10xk.htm", "entities": [{"companyName": "HOME DEPOT INC (Filer)", "cik": "354950", "irsNo": "953261426", "stateOfIncorporation": "DE", "fiscalYearEnd": "0131", "type": "10-K", "act": "34", "fileNo": "001-08207", "filmNo": "161527102", "sic": "5211 Retail-Lumber &amp; Other Building Materials Dealers"}], "documentFormatFiles": [{"sequence": "1", "description": "10-K", "documentUrl": "https://www.sec.gov/Archives/edgar/data/354950/000035495016000060/hd-1312016x10xk.htm", "type": "10-K", "size": "1900500"}, {"sequence": "2", "description": "EMPLOYMENT ARRANGEMENT BETWEEN MARC D. POWERS AND THE HOME DEPOT, INC.", "documentUrl": "https://www.sec.gov/Archives/edgar/data/354950/000035495016000060/hd-1312016xexx1034.htm", "type": "EX-10.34", "size": "32668"}, {"sequence": "3", "description": "SEPARATION AGREEMENT & RELEASE BETWEEN MARC D. POWERS AND THE HOME DEPOT, INC.", "documentUrl": "https://www.sec.gov/Archives/edgar/data/354950/000035495016000060/hd-1312016xexx1035.htm", "type": "EX-10.35", "size": "74122"}, {"sequence": "4", "description": "STATEMENT OF COMPUTATION OF RATIO OF EARNINGS TO FIXED CHARGES", "documentUrl": "https://www.sec.gov/Archives/edgar/data/354950/000035495016000060/hd-1312016xexx12.htm", "type": "EX-12", "size": "49240"}, {"sequence": "5", "description": "LIST OF SUBSIDIARIES OF THE COMPANY", "documentUrl": "https://www.sec.gov/Archives/edgar/data/354950/000035495016000060/hd-1312016xexx21.htm", "type": "EX-21", "size": "11806"}, {"sequence": "6", "description": "CONSENT OF INDEPENDENT REGISTERED PUBLIC ACCOUNTING FIRM", "documentUrl": "https://www.sec.gov/Archives/edgar/data/354950/000035495016000060/hd-1312016xexx23.htm", "type": "EX-23", "size": "4250"}, {"sequence": "7", "description": "CERTIFICATION OF THE CEO", "documentUrl": "https://www.sec.gov/Archives/edgar/data/354950/000035495016000060/hd-1312016xexx311.htm", "type": "EX-31.1", "size": "12691"}, {"sequence": "8", "description": "CERTIFICATION OF THE CFO", "documentUrl": "https://www.sec.gov/Archives/edgar/data/354950/000035495016000060/hd-1312016xexx312.htm", "type": "EX-31.2", "size": "13054"}, {"sequence": "9", "description": "SECTION 906 CERTIFICATION OF THE CEO", "documentUrl": "https://www.sec.gov/Archives/edgar/data/354950/000035495016000060/hd-1312016xexx321.htm", "type": "EX-32.1", "size": "5905"}, {"sequence": "10", "description": "SECTION 906 CERTIFICATION OF THE CFO", "documentUrl": "https://www.sec.gov/Archives/edgar/data/354950/000035495016000060/hd-1312016xexx322.htm", "type": "EX-32.2", "size": "5851"}, {"sequence": "17", "description": "STOCK PERFORMANCE GRAPH", "documentUrl": "https://www.sec.gov/Archives/edgar/data/354950/000035495016000060/hd-222014x1_chartx19303a03.jpg", "type": "GRAPHIC", "size": "71971"}, {"sequence": "\u00a0", "description": "Complete submission text file", "documentUrl": "https://www.sec.gov/Archives/edgar/data/354950/000035495016000060/0000354950-16-000060.txt", "type": "\u00a0", "size": "9384092"}], "dataFiles": [{"sequence": "11", "description": "XBRL INSTANCE DOCUMENT", "documentUrl": "https://www.sec.gov/Archives/edgar/data/354950/000035495016000060/hd-20160131.xml", "type": "EX-101.INS", "size": "1877773"}, {"sequence": "12", "description": "XBRL TAXONOMY EXTENSION SCHEMA DOCUMENT", "documentUrl": "https://www.sec.gov/Archives/edgar/data/354950/000035495016000060/hd-20160131.xsd", "type": "EX-101.SCH", "size": "58830"}, {"sequence": "13", "description": "XBRL TAXONOMY EXTENSION CALCULATION LINKBASE DOCUMENT", "documentUrl": "https://www.sec.gov/Archives/edgar/data/354950/000035495016000060/hd-20160131_cal.xml", "type": "EX-101.CAL", "size": "109495"}, {"sequence": "14", "description": "XBRL TAXONOMY EXTENSION DEFINITION LINKBASE DOCUMENT", "documentUrl": "https://www.sec.gov/Archives/edgar/data/354950/000035495016000060/hd-20160131_def.xml", "type": "EX-101.DEF", "size": "294524"}, {"sequence": "15", "description": "XBRL TAXONOMY EXTENSION LABEL LINKBASE DOCUMENT", "documentUrl": "https://www.sec.gov/Archives/edgar/data/354950/000035495016000060/hd-20160131_lab.xml", "type": "EX-101.LAB", "size": "918594"}, {"sequence": "16", "description": "XBRL TAXONOMY EXTENSION PRESENTATION LINKBASE DOCUMENT", "documentUrl": "https://www.sec.gov/Archives/edgar/data/354950/000035495016000060/hd-20160131_pre.xml", "type": "EX-101.PRE", "size": "508274"}], "seriesAndClassesContractsInformation": [], "periodOfReport": "2016-01-31"}, {"id": "c76115f2c8a55112ba63cb42a86b3c33", "accessionNo": "0000354950-17-000005", "cik": "354950", "ticker": "HD", "companyName": "HOME DEPOT INC", "companyNameLong": "HOME DEPOT INC (Filer)", "formType": "10-K", "description": "Form 10-K - Annual report [Section 13 and 15(d), not S-K Item 405]", "filedAt": "2017-03-23T16:29:46-04:00", "linkToTxt": "https://www.sec.gov/Archives/edgar/data/354950/000035495017000005/0000354950-17-000005.txt", "linkToHtml": "https://www.sec.gov/Archives/edgar/data/354950/0000354950-17-000005-index.htm", "linkToXbrl": "", "linkToFilingDetails": "https://www.sec.gov/Archives/edgar/data/354950/000035495017000005/hd-01292017x10xk.htm", "entities": [{"companyName": "HOME DEPOT INC (Filer)", "cik": "354950", "irsNo": "953261426", "stateOfIncorporation": "DE", "fiscalYearEnd": "0131", "type": "10-K", "act": "34", "fileNo": "001-08207", "filmNo": "17710037", "sic": "5211 Retail-Lumber &amp; Other Building Materials Dealers"}], "documentFormatFiles": [{"sequence": "1", "description": "10-K", "documentUrl": "https://www.sec.gov/Archives/edgar/data/354950/000035495017000005/hd-01292017x10xk.htm", "type": "10-K", "size": "1888130"}, {"sequence": "2", "description": "FORM OF DEFERRED SHARE AWARD (NON-EMPLOYEE DIRECTOR) PURSUANT TO THE HOME DEPOT", "documentUrl": "https://www.sec.gov/Archives/edgar/data/354950/000035495017000005/hd-01292017xexx1021.htm", "type": "EX-10.21", "size": "28934"}, {"sequence": "3", "description": "EMPLOYMENT ARRANGEMENT BETWEEN ANN-MARIE CAMPBELL AND THE HOME DEPOT, INC.", "documentUrl": "https://www.sec.gov/Archives/edgar/data/354950/000035495017000005/hd-01292017xexx1029.htm", "type": "EX-10.29", "size": "34971"}, {"sequence": "4", "description": "STATEMENT OF COMPUTATION OF RATIO OF EARNINGS TO FIXED CHARGES", "documentUrl": "https://www.sec.gov/Archives/edgar/data/354950/000035495017000005/hd-01292017xexx12.htm", "type": "EX-12", "size": "49663"}, {"sequence": "5", "description": "LIST OF SUBSIDIARIES OF THE COMPANY", "documentUrl": "https://www.sec.gov/Archives/edgar/data/354950/000035495017000005/hd-01292017xexx21.htm", "type": "EX-21", "size": "10706"}, {"sequence": "6", "description": "CONSENT OF INDEPENDENT REGISTERED PUBLIC ACCOUNTING FIRM", "documentUrl": "https://www.sec.gov/Archives/edgar/data/354950/000035495017000005/hd-01292017xexx23.htm", "type": "EX-23", "size": "4154"}, {"sequence": "7", "description": "CERTIFICATION OF THE CEO", "documentUrl": "https://www.sec.gov/Archives/edgar/data/354950/000035495017000005/hd-01292017xexx311.htm", "type": "EX-31.1", "size": "12739"}, {"sequence": "8", "description": "CERTIFICATION OF THE CFO", "documentUrl": "https://www.sec.gov/Archives/edgar/data/354950/000035495017000005/hd-01292017xexx312.htm", "type": "EX-31.2", "size": "13102"}, {"sequence": "9", "description": "SECTION 906 CERTIFICATION OF THE CEO", "documentUrl": "https://www.sec.gov/Archives/edgar/data/354950/000035495017000005/hd-01292017xexx321.htm", "type": "EX-32.1", "size": "5946"}, {"sequence": "10", "description": "SECTION 906 CERTIFICATION OF THE CFO", "documentUrl": "https://www.sec.gov/Archives/edgar/data/354950/000035495017000005/hd-01292017xexx322.htm", "type": "EX-32.2", "size": "5892"}, {"sequence": "17", "description": "STOCK PERFORMANCE GRAPH", "documentUrl": "https://www.sec.gov/Archives/edgar/data/354950/000035495017000005/hd-01292017_chartx58681.jpg", "type": "GRAPHIC", "size": "72414"}, {"sequence": "\u00a0", "description": "Complete submission text file", "documentUrl": "https://www.sec.gov/Archives/edgar/data/354950/000035495017000005/0000354950-17-000005.txt", "type": "\u00a0", "size": "9136551"}], "dataFiles": [{"sequence": "11", "description": "XBRL INSTANCE DOCUMENT", "documentUrl": "https://www.sec.gov/Archives/edgar/data/354950/000035495017000005/hd-20170129.xml", "type": "EX-101.INS", "size": "1744031"}, {"sequence": "12", "description": "XBRL TAXONOMY EXTENSION SCHEMA DOCUMENT", "documentUrl": "https://www.sec.gov/Archives/edgar/data/354950/000035495017000005/hd-20170129.xsd", "type": "EX-101.SCH", "size": "58047"}, {"sequence": "13", "description": "XBRL TAXONOMY EXTENSION CALCULATION LINKBASE DOCUMENT", "documentUrl": "https://www.sec.gov/Archives/edgar/data/354950/000035495017000005/hd-20170129_cal.xml", "type": "EX-101.CAL", "size": "110041"}, {"sequence": "14", "description": "XBRL TAXONOMY EXTENSION DEFINITION LINKBASE DOCUMENT", "documentUrl": "https://www.sec.gov/Archives/edgar/data/354950/000035495017000005/hd-20170129_def.xml", "type": "EX-101.DEF", "size": "306911"}, {"sequence": "15", "description": "XBRL TAXONOMY EXTENSION LABEL LINKBASE DOCUMENT", "documentUrl": "https://www.sec.gov/Archives/edgar/data/354950/000035495017000005/hd-20170129_lab.xml", "type": "EX-101.LAB", "size": "924829"}, {"sequence": "16", "description": "XBRL TAXONOMY EXTENSION PRESENTATION LINKBASE DOCUMENT", "documentUrl": "https://www.sec.gov/Archives/edgar/data/354950/000035495017000005/hd-20170129_pre.xml", "type": "EX-101.PRE", "size": "521748"}], "seriesAndClassesContractsInformation": [], "periodOfReport": "2017-01-29"}, {"id": "343540102dee4ead50b989e5a835ab28", "accessionNo": "0000354950-18-000019", "cik": "354950", "ticker": "HD", "companyName": "HOME DEPOT INC", "companyNameLong": "HOME DEPOT INC (Filer)", "formType": "10-K", "description": "Form 10-K - Annual report [Section 13 and 15(d), not S-K Item 405]", "filedAt": "2018-03-22T16:56:00-04:00", "linkToTxt": "https://www.sec.gov/Archives/edgar/data/354950/000035495018000019/0000354950-18-000019.txt", "linkToHtml": "https://www.sec.gov/Archives/edgar/data/354950/0000354950-18-000019-index.htm", "linkToXbrl": "", "linkToFilingDetails": "https://www.sec.gov/Archives/edgar/data/354950/000035495018000019/hd_10k01282018.htm", "entities": [{"companyName": "HOME DEPOT INC (Filer)", "cik": "354950", "irsNo": "953261426", "stateOfIncorporation": "DE", "fiscalYearEnd": "0131", "type": "10-K", "act": "34", "fileNo": "001-08207", "filmNo": "18707512", "sic": "5211 Retail-Lumber &amp; Other Building Materials Dealers"}], "documentFormatFiles": [{"sequence": "1", "description": "10-K", "documentUrl": "https://www.sec.gov/Archives/edgar/data/354950/000035495018000019/hd_10k01282018.htm", "type": "10-K", "size": "1896088"}, {"sequence": "2", "description": "EMPLOYMENT ARRANGEMENT BETWEEN EDWARD P. DECKER AND THE HOME DEPOT, INC.", "documentUrl": "https://www.sec.gov/Archives/edgar/data/354950/000035495018000019/hd_01282018xexhibit1031.htm", "type": "EX-10.31", "size": "23296"}, {"sequence": "3", "description": "STATEMENT OF COMPUTATION OF RATIO OF EARNINGS TO FIXED CHARGES", "documentUrl": "https://www.sec.gov/Archives/edgar/data/354950/000035495018000019/hd_01282018xexhibit12.htm", "type": "EX-12", "size": "36866"}, {"sequence": "4", "description": "LIST OF SUBSIDIARIES OF THE COMPANY", "documentUrl": "https://www.sec.gov/Archives/edgar/data/354950/000035495018000019/hd_01282018xexhibit21.htm", "type": "EX-21", "size": "7229"}, {"sequence": "5", "description": "CONSENT OF INDEPENDENT REGISTERED PUBLIC ACCOUNTING FIRM", "documentUrl": "https://www.sec.gov/Archives/edgar/data/354950/000035495018000019/hd_01282018xexhibit23.htm", "type": "EX-23", "size": "5407"}, {"sequence": "6", "description": "CERTIFICATION OF THE CEO", "documentUrl": "https://www.sec.gov/Archives/edgar/data/354950/000035495018000019/hd_01282018xexhibit311.htm", "type": "EX-31.1", "size": "12070"}, {"sequence": "7", "description": "CERTIFICATION OF THE CFO", "documentUrl": "https://www.sec.gov/Archives/edgar/data/354950/000035495018000019/hd_01282018xexhibit312.htm", "type": "EX-31.2", "size": "12341"}, {"sequence": "8", "description": "SECTION 906 CERTIFICATION OF THE CEO", "documentUrl": "https://www.sec.gov/Archives/edgar/data/354950/000035495018000019/hd_01282018xexhibit321.htm", "type": "EX-32.1", "size": "6077"}, {"sequence": "9", "description": "SECTION 906 CERTIFICATION OF THE CFO", "documentUrl": "https://www.sec.gov/Archives/edgar/data/354950/000035495018000019/hd_01282018xexhibit322.htm", "type": "EX-32.2", "size": "6579"}, {"sequence": "16", "description": "CASH FLOWS SUMMARY GRAPH", "documentUrl": "https://www.sec.gov/Archives/edgar/data/354950/000035495018000019/chart-5b126f5c8d36dbb6f97.jpg", "type": "GRAPHIC", "size": "56344"}, {"sequence": "17", "description": "STOCK PERFORMANCE GRAPH", "documentUrl": "https://www.sec.gov/Archives/edgar/data/354950/000035495018000019/chart-85f6f2906384551ba7b.jpg", "type": "GRAPHIC", "size": "60911"}, {"sequence": "18", "description": "THD LOGO", "documentUrl": "https://www.sec.gov/Archives/edgar/data/354950/000035495018000019/thdpms5prcntrulemediuma02.jpg", "type": "GRAPHIC", "size": "1078756"}, {"sequence": "\u00a0", "description": "Complete submission text file", "documentUrl": "https://www.sec.gov/Archives/edgar/data/354950/000035495018000019/0000354950-18-000019.txt", "type": "\u00a0", "size": "11277492"}], "dataFiles": [{"sequence": "10", "description": "XBRL INSTANCE DOCUMENT", "documentUrl": "https://www.sec.gov/Archives/edgar/data/354950/000035495018000019/hd-20180128.xml", "type": "EX-101.INS", "size": "2072648"}, {"sequence": "11", "description": "XBRL TAXONOMY EXTENSION SCHEMA DOCUMENT", "documentUrl": "https://www.sec.gov/Archives/edgar/data/354950/000035495018000019/hd-20180128.xsd", "type": "EX-101.SCH", "size": "64719"}, {"sequence": "12", "description": "XBRL TAXONOMY EXTENSION CALCULATION LINKBASE DOCUMENT", "documentUrl": "https://www.sec.gov/Archives/edgar/data/354950/000035495018000019/hd-20180128_cal.xml", "type": "EX-101.CAL", "size": "110767"}, {"sequence": "13", "description": "XBRL TAXONOMY EXTENSION DEFINITION LINKBASE DOCUMENT", "documentUrl": "https://www.sec.gov/Archives/edgar/data/354950/000035495018000019/hd-20180128_def.xml", "type": "EX-101.DEF", "size": "305296"}, {"sequence": "14", "description": "XBRL TAXONOMY EXTENSION LABEL LINKBASE DOCUMENT", "documentUrl": "https://www.sec.gov/Archives/edgar/data/354950/000035495018000019/hd-20180128_lab.xml", "type": "EX-101.LAB", "size": "905440"}, {"sequence": "15", "description": "XBRL TAXONOMY EXTENSION PRESENTATION LINKBASE DOCUMENT", "documentUrl": "https://www.sec.gov/Archives/edgar/data/354950/000035495018000019/hd-20180128_pre.xml", "type": "EX-101.PRE", "size": "531200"}], "seriesAndClassesContractsInformation": [], "periodOfReport": "2018-01-28"}, {"id": "9e4d3338172b87f15e10cc9d50db7ef0", "accessionNo": "0000354950-19-000010", "cik": "354950", "ticker": "HD", "companyName": "HOME DEPOT INC", "companyNameLong": "HOME DEPOT INC (Filer)", "formType": "10-K", "description": "Form 10-K - Annual report [Section 13 and 15(d), not S-K Item 405]", "filedAt": "2019-03-28T16:42:29-04:00", "linkToTxt": "https://www.sec.gov/Archives/edgar/data/354950/000035495019000010/0000354950-19-000010.txt", "linkToHtml": "https://www.sec.gov/Archives/edgar/data/354950/0000354950-19-000010-index.htm", "linkToXbrl": "", "linkToFilingDetails": "https://www.sec.gov/Archives/edgar/data/354950/000035495019000010/hd_10kx02032019.htm", "entities": [{"companyName": "HOME DEPOT INC (Filer)", "cik": "354950", "irsNo": "953261426", "stateOfIncorporation": "DE", "fiscalYearEnd": "0203", "type": "10-K", "act": "34", "fileNo": "001-08207", "filmNo": "19712514", "sic": "5211 Retail-Lumber &amp; Other Building Materials Dealers"}], "documentFormatFiles": [{"sequence": "1", "description": "10-K", "documentUrl": "https://www.sec.gov/Archives/edgar/data/354950/000035495019000010/hd_10kx02032019.htm", "type": "10-K", "size": "2039748"}, {"sequence": "2", "description": "EXHIBIT 21", "documentUrl": "https://www.sec.gov/Archives/edgar/data/354950/000035495019000010/hd_exhibit21x02032019.htm", "type": "EX-21", "size": "7204"}, {"sequence": "3", "description": "EXHIBIT 23", "documentUrl": "https://www.sec.gov/Archives/edgar/data/354950/000035495019000010/hd_exhibit23x02032019.htm", "type": "EX-23", "size": "5471"}, {"sequence": "4", "description": "EXHIBIT 31.1", "documentUrl": "https://www.sec.gov/Archives/edgar/data/354950/000035495019000010/hd_exhibit311x02032019.htm", "type": "EX-31.1", "size": "12575"}, {"sequence": "5", "description": "EXHIBIT 31.2", "documentUrl": "https://www.sec.gov/Archives/edgar/data/354950/000035495019000010/hd_exhibit312x02032019.htm", "type": "EX-31.2", "size": "12870"}, {"sequence": "6", "description": "EXHIBIT 32.1", "documentUrl": "https://www.sec.gov/Archives/edgar/data/354950/000035495019000010/hd_exhibit321x02032019.htm", "type": "EX-32.1", "size": "5854"}, {"sequence": "7", "description": "EXHIBIT 32.2", "documentUrl": "https://www.sec.gov/Archives/edgar/data/354950/000035495019000010/hd_exhibit322x02032019.htm", "type": "EX-32.2", "size": "6223"}, {"sequence": "14", "documentUrl": "https://www.sec.gov/Archives/edgar/data/354950/000035495019000010/chart-8cc2262fdd295d77ad0.jpg", "type": "GRAPHIC", "size": "47222"}, {"sequence": "15", "documentUrl": "https://www.sec.gov/Archives/edgar/data/354950/000035495019000010/chart-d90fffb821f256df835.jpg", "type": "GRAPHIC", "size": "54448"}, {"sequence": "16", "documentUrl": "https://www.sec.gov/Archives/edgar/data/354950/000035495019000010/thdpms5prcntrulemediuma11.jpg", "type": "GRAPHIC", "size": "1078756"}, {"sequence": "\u00a0", "description": "Complete submission text file", "documentUrl": "https://www.sec.gov/Archives/edgar/data/354950/000035495019000010/0000354950-19-000010.txt", "type": "\u00a0", "size": "11664158"}], "dataFiles": [{"sequence": "8", "description": "XBRL INSTANCE DOCUMENT", "documentUrl": "https://www.sec.gov/Archives/edgar/data/354950/000035495019000010/hd-20190203.xml", "type": "EX-101.INS", "size": "2309272"}, {"sequence": "9", "description": "XBRL TAXONOMY EXTENSION SCHEMA DOCUMENT", "documentUrl": "https://www.sec.gov/Archives/edgar/data/354950/000035495019000010/hd-20190203.xsd", "type": "EX-101.SCH", "size": "62229"}, {"sequence": "10", "description": "XBRL TAXONOMY EXTENSION CALCULATION LINKBASE DOCUMENT", "documentUrl": "https://www.sec.gov/Archives/edgar/data/354950/000035495019000010/hd-20190203_cal.xml", "type": "EX-101.CAL", "size": "105196"}, {"sequence": "11", "description": "XBRL TAXONOMY EXTENSION DEFINITION LINKBASE DOCUMENT", "documentUrl": "https://www.sec.gov/Archives/edgar/data/354950/000035495019000010/hd-20190203_def.xml", "type": "EX-101.DEF", "size": "286659"}, {"sequence": "12", "description": "XBRL TAXONOMY EXTENSION LABEL LINKBASE DOCUMENT", "documentUrl": "https://www.sec.gov/Archives/edgar/data/354950/000035495019000010/hd-20190203_lab.xml", "type": "EX-101.LAB", "size": "895929"}, {"sequence": "13", "description": "XBRL TAXONOMY EXTENSION PRESENTATION LINKBASE DOCUMENT", "documentUrl": "https://www.sec.gov/Archives/edgar/data/354950/000035495019000010/hd-20190203_pre.xml", "type": "EX-101.PRE", "size": "516912"}], "seriesAndClassesContractsInformation": [], "periodOfReport": "2019-02-03"}]}